{
  "plans": [
    {
      "type": "Web Hosting",
      "name": "Basic",
      "period": "yearly",
      "price": 2995,
      "monthlyBreakdown": 249,
      "currency": "৳",
      "features": [
        "2 Hosted Domains",
        "Unlimited Email Accounts",
        "2 MySQL Databases",
        "Latest Control Panel",
        "CloudLinux OS"
      ],
      "server": [
        "99.9% Uptime Guarantee",
        "1 Core Hosting CPU",
        "1 GB Hosting RAM",
        "5 MBPS I/O Speed",
        "10 EP (Entry Process)",
        "50 Max Processes",
        "No SSH/Terminal Access"
      ]
    },
    {
      "type": "Web Hosting",
      "name": "Starter",
      "period": "yearly",
      "price": 4740,
      "monthlyBreakdown": 395,
      "currency": "৳",
      "features": [
        "5 Hosted Domains",
        "Unlimited Email Accounts",
        "5 MySQL Databases",
        "Latest Control Panel",
        "CloudLinux OS"
      ],
      "server": [
        "99.9% Uptime Guarantee",
        "2 Core Hosting CPU",
        "2 GB Hosting RAM",
        "15 MBPS I/O Speed",
        "20 EP (Entry Process)",
        "100 Max Processes",
        "No SSH/Terminal Access"
      ]
    },
    {
      "type": "Web Hosting",
      "name": "Pro",
      "period": "yearly",
      "price": 7188,
      "monthlyBreakdown": 599,
      "currency": "৳",
      "features": [
        "Unlimited Hosted Domains",
        "Unlimited Email Accounts",
        "Unlimited MySQL Databases",
        "Latest Control Panel",
        "CloudLinux OS"
      ],
      "server": [
        "99.9% Uptime Guarantee",
        "3 Core Hosting CPU",
        "3 GB Hosting RAM",
        "25 MBPS I/O Speed",
        "50 EP (Entry Process)",
        "150 Max Processes",
        "SSH/Terminal Access Included"
      ]
    },
    {
      "type": "Web Hosting",
      "name": "Ultimate",
      "period": "yearly",
      "price": 10548,
      "monthlyBreakdown": 879,
      "currency": "৳",
      "features": [
        "Unlimited Hosted Domains",
        "Unlimited Email Accounts",
        "Unlimited MySQL Databases",
        "Latest Control Panel",
        "CloudLinux OS"
      ],
      "server": [
        "99.9% Uptime Guarantee",
        "4 Core Hosting CPU",
        "4 GB Hosting RAM",
        "50 MBPS I/O Speed",
        "100 EP (Entry Process)",
        "200 Max Processes",
        "SSH/Terminal Access Included"
      ]
    },
    {
      "type": "Web Hosting",
      "name": "Basic",
      "period": "monthly",
      "price": 799,
      "monthlyBreakdown": 799,
      "currency": "৳",
      "features": [
        "2 Hosted Domains",
        "Unlimited Email Accounts",
        "2 MySQL Databases",
        "Latest Control Panel",
        "CloudLinux OS"
      ],
      "server": [
        "99.9% Uptime Guarantee",
        "1 Core Hosting CPU",
        "1 GB Hosting RAM",
        "5 MBPS I/O Speed",
        "10 EP (Entry Process)",
        "50 Max Processes",
        "No SSH/Terminal Access"
      ]
    },
    {
      "type": "Web Hosting",
      "name": "Starter",
      "period": "monthly",
      "price": 1499,
      "monthlyBreakdown": 1499,
      "currency": "৳",
      "features": [
        "5 Hosted Domains",
        "Unlimited Email Accounts",
        "5 MySQL Databases",
        "Latest Control Panel",
        "CloudLinux OS"
      ],
      "server": [
        "99.9% Uptime Guarantee",
        "2 Core Hosting CPU",
        "2 GB Hosting RAM",
        "15 MBPS I/O Speed",
        "20 EP (Entry Process)",
        "100 Max Processes",
        "No SSH/Terminal Access"
      ]
    },
    {
      "type": "Web Hosting",
      "name": "Pro",
      "period": "monthly",
      "price": 2499,
      "monthlyBreakdown": 2499,
      "currency": "৳",
      "features": [
        "Unlimited Hosted Domains",
        "Unlimited Email Accounts",
        "Unlimited MySQL Databases",
        "Latest Control Panel",
        "CloudLinux OS"
      ],
      "server": [
        "99.9% Uptime Guarantee",
        "3 Core Hosting CPU",
        "3 GB Hosting RAM",
        "25 MBPS I/O Speed",
        "50 EP (Entry Process)",
        "150 Max Processes",
        "SSH/Terminal Access Included"
      ]
    },
    {
      "type": "Web Hosting",
      "name": "Ultimate",
      "period": "monthly",
      "price": 4999,
      "monthlyBreakdown": 4999,
      "currency": "৳",
      "features": [
        "Unlimited Hosted Domains",
        "Unlimited Email Accounts",
        "Unlimited MySQL Databases",
        "Latest Control Panel",
        "CloudLinux OS"
      ],
      "server": [
        "99.9% Uptime Guarantee",
        "4 Core Hosting CPU",
        "4 GB Hosting RAM",
        "50 MBPS I/O Speed",
        "100 EP (Entry Process)",
        "200 Max Processes",
        "SSH/Terminal Access Included"
      ]
    },
    {
      "type": "WordPress Hosting",
      "name": "WP Starter",
      "period": "yearly",
      "price": 3588,
      "monthlyBreakdown": 299,
      "currency": "৳",
      "features": [
        "2 Hosted Domains"
      ],
      "server": [
        "1 GB RAM",
        "2 Core Hosting CPU",
        "2 GB Hosting RAM",
        "15 MBPS I/O Speed",
        "20 EP (Entry Process)",
        "50 Max Processes",
        "No SSH/Terminal Access"
      ]
    },
    {
      "type": "WordPress Hosting",
      "name": "WP Pro",
      "period": "yearly",
      "price": 5988,
      "monthlyBreakdown": 499,
      "currency": "৳",
      "features": [
        "5 Hosted Domains"
      ],
      "server": [
        "2 GB RAM",
        "3 Core Hosting CPU",
        "3 GB Hosting RAM",
        "25 MBPS I/O Speed",
        "50 EP (Entry Process)",
        "100 Max Processes",
        "No SSH/Terminal Access"
      ]
    },
    {
      "type": "WordPress Hosting",
      "name": "WP Ultimate",
      "period": "yearly",
      "price": 11988,
      "monthlyBreakdown": 999,
      "currency": "৳",
      "features": [
        "Unlimited Hosted Domains"
      ],
      "server": [
        "4 GB RAM",
        "4 Core Hosting CPU",
        "4 GB Hosting RAM",
        "50 MBPS I/O Speed",
        "100 EP (Entry Process)",
        "150 Max Processes",
        "SSH/Terminal Access Included"
      ]
    },
    {
      "type": "WordPress Hosting",
      "name": "WP Starter",
      "period": "monthly",
      "price": 599,
      "monthlyBreakdown": 599,
      "currency": "৳",
      "features": [
        "2 Hosted Domains"
      ],
      "server": [
        "1 GB RAM",
        "2 Core Hosting CPU",
        "2 GB Hosting RAM",
        "15 MBPS I/O Speed",
        "20 EP (Entry Process)",
        "50 Max Processes",
        "No SSH/Terminal Access"
      ]
    },
    {
      "type": "WordPress Hosting",
      "name": "WP Pro",
      "period": "monthly",
      "price": 999,
      "monthlyBreakdown": 999,
      "currency": "৳",
      "features": [
        "5 Hosted Domains"
      ],
      "server": [
        "2 GB RAM",
        "3 Core Hosting CPU",
        "3 GB Hosting RAM",
        "25 MBPS I/O Speed",
        "50 EP (Entry Process)",
        "100 Max Processes",
        "No SSH/Terminal Access"
      ]
    },
    {
      "type": "WordPress Hosting",
      "name": "WP Ultimate",
      "period": "monthly",
      "price": 1999,
      "monthlyBreakdown": 1999,
      "currency": "৳",
      "features": [
        "Unlimited Hosted Domains"
      ],
      "server": [
        "4 GB RAM",
        "4 Core Hosting CPU",
        "4 GB Hosting RAM",
        "50 MBPS I/O Speed",
        "100 EP (Entry Process)",
        "150 Max Processes",
        "SSH/Terminal Access Included"
      ]
    },
    {
      "type": "BDIX Hosting",
      "name": "Basic",
      "period": "yearly",
      "price": 3588,
      "monthlyBreakdown": 299,
      "currency": "৳",
      "features": [
        "2 Hosted Domains"
      ],
      "server": [
        "99.9% Uptime",
        "1 Core CPU",
        "1 GB RAM",
        "5 MBPS I/O",
        "10 Entry Process",
        "50 Max Processes",
        "No SSH/Terminal Access"
      ]
    },
    {
      "type": "BDIX Hosting",
      "name": "Starter",
      "period": "yearly",
      "price": 5628,
      "monthlyBreakdown": 469,
      "currency": "৳",
      "features": [
        "5 Hosted Domains"
      ],
      "server": [
        "99.9% Uptime",
        "2 Core CPU",
        "2 GB RAM",
        "15 MBPS I/O",
        "20 Entry Process",
        "100 Max Processes",
        "No SSH/Terminal Access"
      ]
    },
    {
      "type": "BDIX Hosting",
      "name": "Pro",
      "period": "yearly",
      "price": 8628,
      "monthlyBreakdown": 719,
      "currency": "৳",
      "features": [
        "Unlimited Hosted Domains"
      ],
      "server": [
        "99.9% Uptime",
        "3 Core CPU",
        "3 GB RAM",
        "25 MBPS I/O",
        "50 Entry Process",
        "150 Max Processes",
        "SSH/Terminal Access Included"
      ]
    },
    {
      "type": "BDIX Hosting",
      "name": "Ultimate",
      "period": "yearly",
      "price": 12588,
      "monthlyBreakdown": 1049,
      "currency": "৳",
      "features": [
        "Unlimited Hosted Domains"
      ],
      "server": [
        "99.9% Uptime",
        "4 Core CPU",
        "4 GB RAM",
        "50 MBPS I/O",
        "80 Entry Process",
        "200 Max Processes",
        "SSH/Terminal Access Included"
      ]
    },
    {
      "type": "BDIX Hosting",
      "name": "Basic",
      "period": "monthly",
      "price": 999,
      "monthlyBreakdown": 999,
      "currency": "৳",
      "features": [
        "2 Hosted Domains"
      ],
      "server": [
        "99.9% Uptime",
        "1 Core CPU",
        "1 GB RAM",
        "5 MBPS I/O",
        "10 Entry Process",
        "50 Max Processes",
        "No SSH/Terminal Access"
      ]
    },
    {
      "type": "BDIX Hosting",
      "name": "Starter",
      "period": "monthly",
      "price": 1999,
      "monthlyBreakdown": 1999,
      "currency": "৳",
      "features": [
        "5 Hosted Domains"
      ],
      "server": [
        "99.9% Uptime",
        "2 Core CPU",
        "2 GB RAM",
        "15 MBPS I/O",
        "20 Entry Process",
        "100 Max Processes",
        "No SSH/Terminal Access"
      ]
    },
    {
      "type": "BDIX Hosting",
      "name": "Pro",
      "period": "monthly",
      "price": 2999,
      "monthlyBreakdown": 2999,
      "currency": "৳",
      "features": [
        "Unlimited Hosted Domains"
      ],
      "server": [
        "99.9% Uptime",
        "3 Core CPU",
        "3 GB RAM",
        "25 MBPS I/O",
        "50 Entry Process",
        "150 Max Processes",
        "SSH/Terminal Access Included"
      ]
    },
    {
      "type": "BDIX Hosting",
      "name": "Ultimate",
      "period": "monthly",
      "price": 5999,
      "monthlyBreakdown": 5999,
      "currency": "৳",
      "features": [
        "Unlimited Hosted Domains"
      ],
      "server": [
        "99.9% Uptime",
        "4 Core CPU",
        "4 GB RAM",
        "50 MBPS I/O",
        "80 Entry Process",
        "200 Max Processes",
        "SSH/Terminal Access Included"
      ]
    },
    {
      "type": "Cloud Hosting",
      "name": "Basic",
      "period": "yearly",
      "price": 7188,
      "monthlyBreakdown": 599,
      "currency": "৳",
      "features": [
        "2 Hosted Domains"
      ],
      "server": [
        "99.9% Uptime",
        "2 Core CPU",
        "2 GB RAM",
        "10 MBPS I/O",
        "15 Entry Process",
        "50 Max Processes",
        "No SSH/Terminal Access"
      ]
    },
    {
      "type": "Cloud Hosting",
      "name": "Starter",
      "period": "yearly",
      "price": 11988,
      "monthlyBreakdown": 999,
      "currency": "৳",
      "features": [
        "5 Hosted Domains"
      ],
      "server": [
        "99.9% Uptime",
        "2 Core CPU",
        "2 GB RAM",
        "10 MBPS I/O",
        "15 Entry Process",
        "100 Max Processes",
        "No SSH/Terminal Access"
      ]
    },
    {
      "type": "Cloud Hosting",
      "name": "Pro",
      "period": "yearly",
      "price": 17988,
      "monthlyBreakdown": 1499,
      "currency": "৳",
      "features": [
        "Unlimited Hosted Domains"
      ],
      "server": [
        "99.9% Uptime",
        "3 Core CPU",
        "3 GB RAM",
        "20 MBPS I/O",
        "30 Entry Process",
        "150 Max Processes",
        "SSH/Terminal Access Included"
      ]
    },
    {
      "type": "Cloud Hosting",
      "name": "Ultimate",
      "period": "yearly",
      "price": 35988,
      "monthlyBreakdown": 2999,
      "currency": "৳",
      "features": [
        "Unlimited Hosted Domains"
      ],
      "server": [
        "99.9% Uptime",
        "4 Core CPU",
        "4 GB RAM",
        "40 MBPS I/O",
        "50 Entry Process",
        "200 Max Processes",
        "SSH/Terminal Access Included"
      ]
    },
    {
      "type": "Cloud Hosting",
      "name": "Basic",
      "period": "monthly",
      "price": 1999,
      "monthlyBreakdown": 1999,
      "currency": "৳",
      "features": [
        "2 Hosted Domains"
      ],
      "server": [
        "99.9% Uptime",
        "2 Core CPU",
        "2 GB RAM",
        "10 MBPS I/O",
        "15 Entry Process",
        "50 Max Processes",
        "No SSH/Terminal Access"
      ]
    },
    {
      "type": "Cloud Hosting",
      "name": "Starter",
      "period": "monthly",
      "price": 2999,
      "monthlyBreakdown": 2999,
      "currency": "৳",
      "features": [
        "5 Hosted Domains"
      ],
      "server": [
        "99.9% Uptime",
        "2 Core CPU",
        "2 GB RAM",
        "10 MBPS I/O",
        "15 Entry Process",
        "100 Max Processes",
        "No SSH/Terminal Access"
      ]
    },
    {
      "type": "Cloud Hosting",
      "name": "Pro",
      "period": "monthly",
      "price": 4999,
      "monthlyBreakdown": 4999,
      "currency": "৳",
      "features": [
        "Unlimited Hosted Domains"
      ],
      "server": [
        "99.9% Uptime",
        "3 Core CPU",
        "3 GB RAM",
        "20 MBPS I/O",
        "30 Entry Process",
        "150 Max Processes",
        "SSH/Terminal Access Included"
      ]
    },
    {
      "type": "Cloud Hosting",
      "name": "Ultimate",
      "period": "monthly",
      "price": 8999,
      "monthlyBreakdown": 8999,
      "currency": "৳",
      "features": [
        "Unlimited Hosted Domains"
      ],
      "server": [
        "99.9% Uptime",
        "4 Core CPU",
        "4 GB RAM",
        "40 MBPS I/O",
        "50 Entry Process",
        "200 Max Processes",
        "SSH/Terminal Access Included"
      ]
    },
    {
      "type": "Turbo NVMe Hosting",
      "name": "Basic",
      "period": "yearly",
      "price": 11832,
      "monthlyBreakdown": 986,
      "currency": "৳",
      "features": [
        "2 Hosted Domains"
      ],
      "server": [
        "99.9% Uptime",
        "4 Core CPU",
        "4 GB RAM",
        "60 MBPS I/O",
        "120 Entry Process",
        "SSH Access Included"
      ]
    },
    {
      "type": "Turbo NVMe Hosting",
      "name": "Starter",
      "period": "yearly",
      "price": 15792,
      "monthlyBreakdown": 1316,
      "currency": "৳",
      "features": [
        "5 Hosted Domains"
      ],
      "server": [
        "99.9% Uptime",
        "6 Core CPU",
        "6 GB RAM",
        "70 MBPS I/O",
        "150 Entry Process",
        "SSH Access Included"
      ]
    },
    {
      "type": "Turbo NVMe Hosting",
      "name": "Pro",
      "period": "yearly",
      "price": 23712,
      "monthlyBreakdown": 1976,
      "currency": "৳",
      "features": [
        "Unlimited Hosted Domains"
      ],
      "server": [
        "99.9% Uptime",
        "8 Core CPU",
        "8 GB RAM",
        "80 MBPS I/O",
        "200 Entry Process",
        "SSH Access Included"
      ]
    },
    {
      "type": "Turbo NVMe Hosting",
      "name": "Ultimate",
      "period": "yearly",
      "price": 39552,
      "monthlyBreakdown": 3296,
      "currency": "৳",
      "features": [
        "Unlimited Hosted Domains"
      ],
      "server": [
        "99.9% Uptime",
        "10 Core CPU",
        "10 GB RAM",
        "100 MBPS I/O",
        "250 Entry Process",
        "SSH Access Included"
      ]
    },
    {
      "type": "Turbo NVMe Hosting",
      "name": "Basic",
      "period": "monthly",
      "price": 2499,
      "monthlyBreakdown": 2499,
      "currency": "৳",
      "features": [
        "2 Hosted Domains"
      ],
      "server": [
        "99.9% Uptime",
        "4 Core CPU",
        "4 GB RAM",
        "60 MBPS I/O",
        "120 Entry Process",
        "SSH Access Included"
      ]
    },
    {
      "type": "Turbo NVMe Hosting",
      "name": "Starter",
      "period": "monthly",
      "price": 3499,
      "monthlyBreakdown": 3499,
      "currency": "৳",
      "features": [
        "5 Hosted Domains"
      ],
      "server": [
        "99.9% Uptime",
        "6 Core CPU",
        "6 GB RAM",
        "70 MBPS I/O",
        "150 Entry Process",
        "SSH Access Included"
      ]
    },
    {
      "type": "Turbo NVMe Hosting",
      "name": "Pro",
      "period": "monthly",
      "price": 4999,
      "monthlyBreakdown": 4999,
      "currency": "৳",
      "features": [
        "Unlimited Hosted Domains"
      ],
      "server": [
        "99.9% Uptime",
        "8 Core CPU",
        "8 GB RAM",
        "80 MBPS I/O",
        "200 Entry Process",
        "SSH Access Included"
      ]
    },
    {
      "type": "Turbo NVMe Hosting",
      "name": "Ultimate",
      "period": "monthly",
      "price": 8999,
      "monthlyBreakdown": 8999,
      "currency": "৳",
      "features": [
        "Unlimited Hosted Domains"
      ],
      "server": [
        "99.9% Uptime",
        "10 Core CPU",
        "10 GB RAM",
        "100 MBPS I/O",
        "250 Entry Process",
        "SSH Access Included"
      ]
    },
    {
      "type": "WooCommerce Hosting",
      "name": "Basic",
      "period": "monthly",
      "price": 999,
      "currency": "৳",
      "features": [
        "2 Hosted Domains"
      ],
      "server": [
        "2 Core CPU",
        "2 GB RAM",
        "10 MBPS I/O",
        "10 Entry Processes",
        "50 Max Processes",
        "No SSH/Terminal Access"
      ]
    },
    {
      "type": "WooCommerce Hosting",
      "name": "Starter",
      "period": "monthly",
      "price": 1999,
      "currency": "৳",
      "features": [
        "5 Hosted Domains"
      ],
      "server": [
        "3 Core CPU",
        "3 GB RAM",
        "25 MBPS I/O",
        "20 Entry Processes",
        "100 Max Processes",
        "No SSH/Terminal Access"
      ]
    },
    {
      "type": "WooCommerce Hosting",
      "name": "Pro",
      "period": "monthly",
      "price": 2999,
      "currency": "৳",
      "features": [
        "Unlimited Hosted Domains"
      ],
      "server": [
        "4 Core CPU",
        "4 GB RAM",
        "50 MBPS I/O",
        "50 Entry Processes",
        "150 Max Processes",
        "SSH/Terminal Access Included"
      ]
    },
    {
      "type": "WooCommerce Hosting",
      "name": "Ultimate",
      "period": "monthly",
      "price": 5999,
      "currency": "৳",
      "features": [
        "Unlimited Hosted Domains"
      ],
      "server": [
        "6 Core CPU",
        "8 GB RAM",
        "100 MBPS I/O",
        "80 Entry Processes",
        "200 Max Processes",
        "SSH/Terminal Access Included"
      ]
    },
    {
      "type": "WooCommerce Hosting",
      "name": "Basic",
      "period": "yearly",
      "price": 6600,
      "monthlyBreakdown": 550,
      "currency": "৳",
      "features": [
        "2 Hosted Domains"
      ],
      "server": [
        "2 Core CPU",
        "2 GB RAM",
        "10 MBPS I/O",
        "10 Entry Processes",
        "50 Max Processes",
        "No SSH/Terminal Access"
      ]
    },
    {
      "type": "WooCommerce Hosting",
      "name": "Starter",
      "period": "yearly",
      "price": 7392,
      "monthlyBreakdown": 616,
      "currency": "৳",
      "features": [
        "5 Hosted Domains"
      ],
      "server": [
        "3 Core CPU",
        "3 GB RAM",
        "25 MBPS I/O",
        "20 Entry Processes",
        "100 Max Processes",
        "No SSH/Terminal Access"
      ]
    },
    {
      "type": "WooCommerce Hosting",
      "name": "Pro",
      "period": "yearly",
      "price": 10296,
      "monthlyBreakdown": 858,
      "currency": "৳",
      "features": [
        "Unlimited Hosted Domains"
      ],
      "server": [
        "4 Core CPU",
        "4 GB RAM",
        "50 MBPS I/O",
        "50 Entry Processes",
        "150 Max Processes",
        "SSH/Terminal Access Included"
      ]
    },
    {
      "type": "WooCommerce Hosting",
      "name": "Ultimate",
      "period": "yearly",
      "price": 19008,
      "monthlyBreakdown": 1584,
      "currency": "৳",
      "features": [
        "Unlimited Hosted Domains"
      ],
      "server": [
        "6 Core CPU",
        "8 GB RAM",
        "100 MBPS I/O",
        "80 Entry Processes",
        "200 Max Processes",
        "SSH/Terminal Access Included"
      ]
    },
    {
      "type": "Node.js Hosting",
      "name": "Starter",
      "period": "monthly",
      "price": 999,
      "monthlyBreakdown": 999,
      "currency": "৳",
      "features": [
        "5 Hosted Domains"
      ],
      "server": [
        "Auto SSL Renewal",
        "DDoS Protection",
        "Daily Automated Backups",
        "99.9% Uptime Guarantee",
        "Global CDN",
        "100 Max Processes",
        "SSH Access Included"
      ]
    },
    {
      "type": "Node.js Hosting",
      "name": "Pro",
      "period": "monthly",
      "price": 1499,
      "monthlyBreakdown": 1499,
      "currency": "৳",
      "features": [
        "Unlimited Hosted Domains"
      ],
      "server": [
        "Auto SSL Renewal",
        "DDoS Protection",
        "Daily Automated Backups",
        "99.9% Uptime Guarantee",
        "Global CDN",
        "150 Max Processes",
        "SSH Access Included"
      ]
    },
    {
      "type": "Node.js Hosting",
      "name": "Developer",
      "period": "monthly",
      "price": 1999,
      "monthlyBreakdown": 1999,
      "currency": "৳",
      "features": [
        "Unlimited Domains"
      ],
      "server": [
        "Auto SSL Renewal",
        "DDoS Protection",
        "Daily Automated Backups",
        "99.9% Uptime Guarantee",
        "Global CDN",
        "SSH Access Included"
      ]
    },
    {
      "type": "Node.js Hosting",
      "name": "Business",
      "period": "monthly",
      "price": 4999,
      "monthlyBreakdown": 4999,
      "currency": "৳",
      "features": [
        "Unlimited Domains"
      ],
      "server": [
        "Auto SSL Renewal",
        "DDoS Protection",
        "Daily Automated Backups",
        "99.9% Uptime Guarantee",
        "Global CDN",
        "SSH Access Included"
      ]
    },
    {
      "type": "Node.js Hosting",
      "name": "Starter",
      "period": "yearly",
      "price": 4740,
      "monthlyBreakdown": 395,
      "currency": "৳",
      "features": [
        "5 Hosted Domains"
      ],
      "server": [
        "Auto SSL Renewal",
        "DDoS Protection",
        "Daily Automated Backups",
        "99.9% Uptime Guarantee",
        "Global CDN",
        "100 Max Processes",
        "SSH Access Included"
      ]
    },
    {
      "type": "Node.js Hosting",
      "name": "Pro",
      "period": "yearly",
      "price": 5928,
      "monthlyBreakdown": 494,
      "currency": "৳",
      "features": [
        "Unlimited Hosted Domains"
      ],
      "server": [
        "Auto SSL Renewal",
        "DDoS Protection",
        "Daily Automated Backups",
        "99.9% Uptime Guarantee",
        "Global CDN",
        "150 Max Processes",
        "SSH Access Included"
      ]
    },
    {
      "type": "Node.js Hosting",
      "name": "Developer",
      "period": "yearly",
      "price": 7116,
      "monthlyBreakdown": 593,
      "currency": "৳",
      "features": [
        "Unlimited Domains"
      ],
      "server": [
        "Auto SSL Renewal",
        "DDoS Protection",
        "Daily Automated Backups",
        "99.9% Uptime Guarantee",
        "Global CDN",
        "SSH Access Included"
      ]
    },
    {
      "type": "Node.js Hosting",
      "name": "Business",
      "period": "yearly",
      "price": 11868,
      "monthlyBreakdown": 989,
      "currency": "৳",
      "features": [
        "Unlimited Domains"
      ],
      "server": [
        "Auto SSL Renewal",
        "DDoS Protection",
        "Daily Automated Backups",
        "99.9% Uptime Guarantee",
        "Global CDN",
        "SSH Access Included"
      ]
    },
    {
      "type": "N8n App Hosting",
      "name": "Starter",
      "period": "monthly",
      "price": 319,
      "currency": "৳",
      "features": [
        "5 Hosted Domains"
      ],
      "server": [
        "Auto SSL Renewal",
        "DDoS Protection",
        "Daily Backups",
        "99.9% Uptime SLA",
        "PostgreSQL Database",
        "100 Max Processes",
        "No SSH/Terminal Access"
      ]
    },
    {
      "type": "N8n App Hosting",
      "name": "Go",
      "period": "monthly",
      "price": 479,
      "currency": "৳",
      "features": [
        "Unlimited Domains"
      ],
      "server": [
        "Auto SSL Renewal",
        "DDoS Protection",
        "Daily Backups",
        "99.9% Uptime SLA",
        "PostgreSQL Database",
        "No SSH/Terminal Access"
      ]
    },
    {
      "type": "N8n App Hosting",
      "name": "Pro",
      "period": "monthly",
      "price": 879,
      "currency": "৳",
      "features": [
        "Unlimited Hosted Domains"
      ],
      "server": [
        "Auto SSL Renewal",
        "DDoS Protection",
        "Daily Backups",
        "99.9% Uptime SLA",
        "PostgreSQL Database",
        "150 Max Processes",
        "SSH/Terminal Access Included"
      ]
    },
    {
      "type": "N8n App Hosting",
      "name": "Ultimate",
      "period": "monthly",
      "price": 1599,
      "currency": "৳",
      "features": [
        "Unlimited Hosted Domains"
      ],
      "server": [
        "Auto SSL Renewal",
        "DDoS Protection",
        "Daily Backups",
        "99.9% Uptime SLA",
        "PostgreSQL Database",
        "200 Max Processes",
        "SSH/Terminal Access Included"
      ]
    },
    {
      "type": "N8n App Hosting",
      "name": "Starter",
      "period": "yearly",
      "price": 1549,
      "monthlyBreakdown": 129,
      "currency": "৳",
      "features": [
        "5 Hosted Domains"
      ],
      "server": [
        "Auto SSL Renewal",
        "DDoS Protection",
        "Daily Backups",
        "99.9% Uptime SLA",
        "PostgreSQL Database",
        "100 Max Processes",
        "No SSH/Terminal Access"
      ]
    },
    {
      "type": "N8n App Hosting",
      "name": "Go",
      "period": "yearly",
      "price": 2549,
      "monthlyBreakdown": 212,
      "currency": "৳",
      "features": [
        "Unlimited Domains"
      ],
      "server": [
        "Auto SSL Renewal",
        "DDoS Protection",
        "Daily Backups",
        "99.9% Uptime SLA",
        "PostgreSQL Database",
        "No SSH/Terminal Access"
      ]
    },
    {
      "type": "N8n App Hosting",
      "name": "Pro",
      "period": "yearly",
      "price": 4699,
      "monthlyBreakdown": 392,
      "currency": "৳",
      "features": [
        "Unlimited Hosted Domains"
      ],
      "server": [
        "Auto SSL Renewal",
        "DDoS Protection",
        "Daily Backups",
        "99.9% Uptime SLA",
        "PostgreSQL Database",
        "150 Max Processes",
        "SSH/Terminal Access Included"
      ]
    },
    {
      "type": "N8n App Hosting",
      "name": "Ultimate",
      "period": "yearly",
      "price": 8399,
      "monthlyBreakdown": 699,
      "currency": "৳",
      "features": [
        "Unlimited Hosted Domains"
      ],
      "server": [
        "Auto SSL Renewal",
        "DDoS Protection",
        "Daily Backups",
        "99.9% Uptime SLA",
        "PostgreSQL Database",
        "200 Max Processes",
        "SSH/Terminal Access Included"
      ]
    },
    {
      "type": "VPS Hosting",
      "name": "Starter (Bangladesh)",
      "period": "monthly",
      "price": 1599,
      "monthlyBreakdown": 1599,
      "currency": "৳",
      "features": [
        "Unlimited Domains",
        "Dedicated IP (IPv4 + IPv6)",
        "Full Root Access",
        "1 Tbps+ DDoS Protection",
        "AMD EPYC™ Processor",
        "ECC RAM",
        "NVMe SSD Storage",
        "24/7/365 Support",
        "Cloud Firewall",
        "Instant Provisioning"
      ],
      "server": [
        "1 vCPU Core",
        "2 GB RAM",
        "25 GB NVMe Storage",
        "500 GB Bandwidth",
        "No SSH/Terminal Access"
      ]
    },
    {
      "type": "VPS Hosting",
      "name": "Plus (Bangladesh)",
      "period": "monthly",
      "price": 3199,
      "monthlyBreakdown": 3199,
      "currency": "৳",
      "features": [
        "Unlimited Domains",
        "Dedicated IP (IPv4 + IPv6)",
        "Full Root Access",
        "1 Tbps+ DDoS Protection",
        "AMD EPYC™ Processor",
        "ECC RAM",
        "NVMe SSD Storage",
        "24/7/365 Support",
        "Cloud Firewall",
        "Instant Provisioning"
      ],
      "server": [
        "2 vCPU Cores",
        "4 GB RAM",
        "50 GB NVMe Storage",
        "1 TB Bandwidth",
        "No SSH/Terminal Access"
      ]
    },
    {
      "type": "VPS Hosting",
      "name": "Pro (Bangladesh)",
      "period": "monthly",
      "price": 5699,
      "monthlyBreakdown": 5699,
      "currency": "৳",
      "features": [
        "Unlimited Domains",
        "Dedicated IP (IPv4 + IPv6)",
        "Full Root Access",
        "1 Tbps+ DDoS Protection",
        "AMD EPYC™ Processor",
        "ECC RAM",
        "NVMe SSD Storage",
        "24/7/365 Support",
        "Cloud Firewall",
        "Instant Provisioning"
      ],
      "server": [
        "4 vCPU Cores",
        "8 GB RAM",
        "100 GB NVMe Storage",
        "2 TB Bandwidth",
        "No SSH/Terminal Access"
      ]
    },
    {
      "type": "VPS Hosting",
      "name": "Ultimate (Bangladesh)",
      "period": "monthly",
      "price": 10999,
      "monthlyBreakdown": 10999,
      "currency": "৳",
      "features": [
        "Unlimited Domains",
        "Dedicated IP (IPv4 + IPv6)",
        "Full Root Access",
        "1 Tbps+ DDoS Protection",
        "AMD EPYC™ Processor",
        "ECC RAM",
        "NVMe SSD Storage",
        "24/7/365 Support",
        "Cloud Firewall",
        "Instant Provisioning"
      ],
      "server": [
        "8 vCPU Cores",
        "16 GB RAM",
        "200 GB NVMe Storage",
        "4 TB Bandwidth",
        "No SSH/Terminal Access"
      ]
    },
    {
      "type": "VPS Hosting",
      "name": "Enterprise (Bangladesh)",
      "period": "monthly",
      "price": 21999,
      "monthlyBreakdown": 21999,
      "currency": "৳",
      "features": [
        "Unlimited Domains",
        "Dedicated IP (IPv4 + IPv6)",
        "Full Root Access",
        "1 Tbps+ DDoS Protection",
        "AMD EPYC™ Processor",
        "ECC RAM",
        "NVMe SSD Storage",
        "24/7/365 Support",
        "Cloud Firewall",
        "Instant Provisioning"
      ],
      "server": [
        "16 vCPU Cores",
        "32 GB RAM",
        "400 GB NVMe Storage",
        "8 TB Bandwidth",
        "No SSH/Terminal Access"
      ]
    },
    {
      "type": "VPS Hosting",
      "name": "Starter (Singapore)",
      "period": "monthly",
      "price": 2759,
      "monthlyBreakdown": 2759,
      "currency": "৳",
      "features": [
        "Unlimited Domains",
        "Dedicated IP (IPv4 + IPv6)",
        "Full Root Access",
        "1 Tbps+ DDoS Protection",
        "AMD EPYC™ Processor",
        "ECC RAM",
        "NVMe SSD Storage",
        "24/7/365 Support",
        "Cloud Firewall",
        "Instant Provisioning"
      ],
      "server": [
        "2 vCPU Cores",
        "4 GB RAM",
        "80 GB NVMe Storage",
        "2 TB Bandwidth",
        "No SSH/Terminal Access"
      ]
    },
    {
      "type": "VPS Hosting",
      "name": "Plus (Singapore)",
      "period": "monthly",
      "price": 5639,
      "monthlyBreakdown": 5639,
      "currency": "৳",
      "features": [
        "Unlimited Domains",
        "Dedicated IP (IPv4 + IPv6)",
        "Full Root Access",
        "1 Tbps+ DDoS Protection",
        "AMD EPYC™ Processor",
        "ECC RAM",
        "NVMe SSD Storage",
        "24/7/365 Support",
        "Cloud Firewall",
        "Instant Provisioning"
      ],
      "server": [
        "4 vCPU Cores",
        "8 GB RAM",
        "160 GB NVMe Storage",
        "4 TB Bandwidth",
        "No SSH/Terminal Access"
      ]
    },
    {
      "type": "VPS Hosting",
      "name": "Pro (Singapore)",
      "period": "monthly",
      "price": 9599,
      "monthlyBreakdown": 9599,
      "currency": "৳",
      "features": [
        "Unlimited Domains",
        "Dedicated IP (IPv4 + IPv6)",
        "Full Root Access",
        "1 Tbps+ DDoS Protection",
        "AMD EPYC™ Processor",
        "ECC RAM",
        "NVMe SSD Storage",
        "24/7/365 Support",
        "Cloud Firewall",
        "Instant Provisioning"
      ],
      "server": [
        "8 vCPU Cores",
        "16 GB RAM",
        "320 GB NVMe Storage",
        "8 TB Bandwidth",
        "No SSH/Terminal Access"
      ]
    },
    {
      "type": "VPS Hosting",
      "name": "Ultimate (Singapore)",
      "period": "monthly",
      "price": 13799,
      "monthlyBreakdown": 13799,
      "currency": "৳",
      "features": [
        "Unlimited Domains",
        "Dedicated IP (IPv4 + IPv6)",
        "Full Root Access",
        "1 Tbps+ DDoS Protection",
        "AMD EPYC™ Processor",
        "ECC RAM",
        "NVMe SSD Storage",
        "24/7/365 Support",
        "Cloud Firewall",
        "Instant Provisioning"
      ],
      "server": [
        "12 vCPU Cores",
        "24 GB RAM",
        "480 GB NVMe Storage",
        "12 TB Bandwidth",
        "No SSH/Terminal Access"
      ]
    },
    {
      "type": "VPS Hosting",
      "name": "Enterprise (Singapore)",
      "period": "monthly",
      "price": 17999,
      "monthlyBreakdown": 17999,
      "currency": "৳",
      "features": [
        "Unlimited Domains",
        "Dedicated IP (IPv4 + IPv6)",
        "Full Root Access",
        "1 Tbps+ DDoS Protection",
        "AMD EPYC™ Processor",
        "ECC RAM",
        "NVMe SSD Storage",
        "24/7/365 Support",
        "Cloud Firewall",
        "Instant Provisioning"
      ],
      "server": [
        "16 vCPU Cores",
        "32 GB RAM",
        "640 GB NVMe Storage",
        "16 TB Bandwidth",
        "No SSH/Terminal Access"
      ]
    },
    {
      "type": "VPS Hosting",
      "name": "Starter (Germany/Finland)",
      "period": "monthly",
      "price": 1559,
      "monthlyBreakdown": 1559,
      "currency": "৳",
      "features": [
        "Unlimited Domains",
        "Dedicated IP (IPv4 + IPv6)",
        "Full Root Access",
        "1 Tbps+ DDoS Protection",
        "AMD EPYC™ Processor",
        "ECC RAM",
        "NVMe SSD Storage",
        "24/7/365 Support",
        "Cloud Firewall",
        "Instant Provisioning"
      ],
      "server": [
        "2 vCPU Cores",
        "4 GB RAM",
        "80 GB NVMe Storage",
        "20 TB Bandwidth",
        "No SSH/Terminal Access"
      ]
    },
    {
      "type": "VPS Hosting",
      "name": "Plus (Germany/Finland)",
      "period": "monthly",
      "price": 2639,
      "monthlyBreakdown": 2639,
      "currency": "৳",
      "features": [
        "Unlimited Domains",
        "Dedicated IP (IPv4 + IPv6)",
        "Full Root Access",
        "1 Tbps+ DDoS Protection",
        "AMD EPYC™ Processor",
        "ECC RAM",
        "NVMe SSD Storage",
        "24/7/365 Support",
        "Cloud Firewall",
        "Instant Provisioning"
      ],
      "server": [
        "4 vCPU Cores",
        "8 GB RAM",
        "160 GB NVMe Storage",
        "20 TB Bandwidth",
        "No SSH/Terminal Access"
      ]
    },
    {
      "type": "VPS Hosting",
      "name": "Pro (Germany/Finland)",
      "period": "monthly",
      "price": 4799,
      "monthlyBreakdown": 4799,
      "currency": "৳",
      "features": [
        "Unlimited Domains",
        "Dedicated IP (IPv4 + IPv6)",
        "Full Root Access",
        "1 Tbps+ DDoS Protection",
        "AMD EPYC™ Processor",
        "ECC RAM",
        "NVMe SSD Storage",
        "24/7/365 Support",
        "Cloud Firewall",
        "Instant Provisioning"
      ],
      "server": [
        "8 vCPU Cores",
        "16 GB RAM",
        "320 GB NVMe Storage",
        "20 TB Bandwidth",
        "No SSH/Terminal Access"
      ]
    },
    {
      "type": "VPS Hosting",
      "name": "Ultimate (Germany/Finland)",
      "period": "monthly",
      "price": 7199,
      "monthlyBreakdown": 7199,
      "currency": "৳",
      "features": [
        "Unlimited Domains",
        "Dedicated IP (IPv4 + IPv6)",
        "Full Root Access",
        "1 Tbps+ DDoS Protection",
        "AMD EPYC™ Processor",
        "ECC RAM",
        "NVMe SSD Storage",
        "24/7/365 Support",
        "Cloud Firewall",
        "Instant Provisioning"
      ],
      "server": [
        "12 vCPU Cores",
        "24 GB RAM",
        "480 GB NVMe Storage",
        "20 TB Bandwidth",
        "No SSH/Terminal Access"
      ]
    },
    {
      "type": "VPS Hosting",
      "name": "Enterprise (Germany/Finland)",
      "period": "monthly",
      "price": 10799,
      "monthlyBreakdown": 10799,
      "currency": "৳",
      "features": [
        "Unlimited Domains",
        "Dedicated IP (IPv4 + IPv6)",
        "Full Root Access",
        "1 Tbps+ DDoS Protection",
        "AMD EPYC™ Processor",
        "ECC RAM",
        "NVMe SSD Storage",
        "24/7/365 Support",
        "Cloud Firewall",
        "Instant Provisioning"
      ],
      "server": [
        "16 vCPU Cores",
        "32 GB RAM",
        "640 GB NVMe Storage",
        "20 TB Bandwidth",
        "No SSH/Terminal Access"
      ]
    },
    {
      "type": "VPS Hosting",
      "name": "Starter (USA)",
      "period": "monthly",
      "price": 1679,
      "monthlyBreakdown": 1679,
      "currency": "৳",
      "features": [
        "Unlimited Domains",
        "Dedicated IP (IPv4 + IPv6)",
        "Full Root Access",
        "1 Tbps+ DDoS Protection",
        "AMD EPYC™ Processor",
        "ECC RAM",
        "NVMe SSD Storage",
        "24/7/365 Support",
        "Cloud Firewall",
        "Instant Provisioning"
      ],
      "server": [
        "2 vCPU Cores",
        "4 GB RAM",
        "80 GB NVMe Storage",
        "20 TB Bandwidth",
        "No SSH/Terminal Access"
      ]
    },
    {
      "type": "VPS Hosting",
      "name": "Plus (USA)",
      "period": "monthly",
      "price": 2999,
      "monthlyBreakdown": 2999,
      "currency": "৳",
      "features": [
        "Unlimited Domains",
        "Dedicated IP (IPv4 + IPv6)",
        "Full Root Access",
        "1 Tbps+ DDoS Protection",
        "AMD EPYC™ Processor",
        "ECC RAM",
        "NVMe SSD Storage",
        "24/7/365 Support",
        "Cloud Firewall",
        "Instant Provisioning"
      ],
      "server": [
        "4 vCPU Cores",
        "8 GB RAM",
        "160 GB NVMe Storage",
        "20 TB Bandwidth",
        "No SSH/Terminal Access"
      ]
    },
    {
      "type": "VPS Hosting",
      "name": "Pro (USA)",
      "period": "monthly",
      "price": 5399,
      "monthlyBreakdown": 5399,
      "currency": "৳",
      "features": [
        "Unlimited Domains",
        "Dedicated IP (IPv4 + IPv6)",
        "Full Root Access",
        "1 Tbps+ DDoS Protection",
        "AMD EPYC™ Processor",
        "ECC RAM",
        "NVMe SSD Storage",
        "24/7/365 Support",
        "Cloud Firewall",
        "Instant Provisioning"
      ],
      "server": [
        "8 vCPU Cores",
        "16 GB RAM",
        "320 GB NVMe Storage",
        "20 TB Bandwidth",
        "No SSH/Terminal Access"
      ]
    },
    {
      "type": "VPS Hosting",
      "name": "Ultimate (USA)",
      "period": "monthly",
      "price": 8399,
      "monthlyBreakdown": 8399,
      "currency": "৳",
      "features": [
        "Unlimited Domains",
        "Dedicated IP (IPv4 + IPv6)",
        "Full Root Access",
        "1 Tbps+ DDoS Protection",
        "AMD EPYC™ Processor",
        "ECC RAM",
        "NVMe SSD Storage",
        "24/7/365 Support",
        "Cloud Firewall",
        "Instant Provisioning"
      ],
      "server": [
        "12 vCPU Cores",
        "24 GB RAM",
        "480 GB NVMe Storage",
        "20 TB Bandwidth",
        "No SSH/Terminal Access"
      ]
    },
    {
      "type": "VPS Hosting",
      "name": "Enterprise (USA)",
      "period": "monthly",
      "price": 11999,
      "monthlyBreakdown": 11999,
      "currency": "৳",
      "features": [
        "Unlimited Domains",
        "Dedicated IP (IPv4 + IPv6)",
        "Full Root Access",
        "1 Tbps+ DDoS Protection",
        "AMD EPYC™ Processor",
        "ECC RAM",
        "NVMe SSD Storage",
        "24/7/365 Support",
        "Cloud Firewall",
        "Instant Provisioning"
      ],
      "server": [
        "16 vCPU Cores",
        "32 GB RAM",
        "640 GB NVMe Storage",
        "20 TB Bandwidth",
        "No SSH/Terminal Access"
      ]
    },
    {
      "type": "Dedicated Server",
      "name": "Starter Pro",
      "period": "monthly",
      "price": 9900,
      "monthlyBreakdown": 9900,
      "currency": "৳",
      "setupFee": 11440,
      "features": [
        "Unlimited Domains",
        "Dedicated IP (IPv4 + IPv6)",
        "Full Root Access",
        "1 Gbit/s Port",
        "In Built Firewall",
        "Linux/Windows Options"
      ],
      "server": [
        "Intel Core i5-13500 (14 Cores)",
        "64 GB RAM",
        "1 TB NVMe",
        "Setup Fee: ৳11440",
        "No SSH/Terminal Access"
      ]
    },
    {
      "type": "Dedicated Server",
      "name": "Business Elite",
      "period": "monthly",
      "price": 16650,
      "monthlyBreakdown": 16650,
      "currency": "৳",
      "setupFee": 11440,
      "features": [
        "Unlimited Domains",
        "Dedicated IP (IPv4 + IPv6)",
        "Full Root Access",
        "1 Gbit/s Port",
        "In Built Firewall",
        "Linux/Windows Options"
      ],
      "server": [
        "Intel Core Ultra 7 265 (20 Cores)",
        "64 GB RAM",
        "2 TB NVMe",
        "Setup Fee: ৳11440",
        "No SSH/Terminal Access"
      ]
    },
    {
      "type": "Dedicated Server",
      "name": "Enterprise RAM",
      "period": "monthly",
      "price": 33525,
      "monthlyBreakdown": 33525,
      "currency": "৳",
      "setupFee": 23010,
      "features": [
        "Unlimited Domains",
        "Dedicated IP (IPv4 + IPv6)",
        "Full Root Access",
        "1 Gbit/s Port",
        "In Built Firewall",
        "Linux/Windows Options"
      ],
      "server": [
        "Intel Xeon Gold 5412U (24 Cores)",
        "256 GB RAM",
        "3.84 TB NVMe",
        "Setup Fee: ৳23010",
        "No SSH/Terminal Access"
      ]
    },
    {
      "type": "Dedicated Server",
      "name": "Enterprise Storage",
      "period": "monthly",
      "price": 33525,
      "monthlyBreakdown": 33525,
      "currency": "৳",
      "setupFee": 23010,
      "features": [
        "Unlimited Domains",
        "Dedicated IP (IPv4 + IPv6)",
        "Full Root Access",
        "1 Gbit/s Port",
        "In Built Firewall",
        "Linux/Windows Options"
      ],
      "server": [
        "Intel Xeon Gold 5412U (24 Cores)",
        "128 GB RAM",
        "7.68 TB NVMe",
        "Setup Fee: ৳23010",
        "No SSH/Terminal Access"
      ]
    },
    {
      "type": "Dedicated Server",
      "name": "Value AMD",
      "period": "monthly",
      "price": 11999,
      "monthlyBreakdown": 11999,
      "currency": "৳",
      "setupFee": 0,
      "features": [
        "Unlimited Domains",
        "Dedicated IP (IPv4 + IPv6)",
        "Full Root Access",
        "1 Gbit/s Port",
        "In Built Firewall",
        "Linux/Windows Options"
      ],
      "server": [
        "AMD Ryzen 5 3600 (6 Cores)",
        "64 GB RAM",
        "1 TB NVMe",
        "Setup Fee: Free Setup",
        "No SSH/Terminal Access"
      ]
    },
    {
      "type": "Dedicated Server",
      "name": "Pro AMD",
      "period": "monthly",
      "price": 11700,
      "monthlyBreakdown": 11700,
      "currency": "৳",
      "setupFee": 11440,
      "features": [
        "Unlimited Domains",
        "Dedicated IP (IPv4 + IPv6)",
        "Full Root Access",
        "1 Gbit/s Port",
        "In Built Firewall",
        "Linux/Windows Options"
      ],
      "server": [
        "AMD Ryzen 7 PRO 8700GE (8 Cores)",
        "64 GB RAM",
        "1 TB NVMe",
        "Setup Fee: ৳11440",
        "No SSH/Terminal Access"
      ]
    },
    {
      "type": "Dedicated Server",
      "name": "Performance Max",
      "period": "monthly",
      "price": 26100,
      "monthlyBreakdown": 26100,
      "currency": "৳",
      "setupFee": 11440,
      "features": [
        "Unlimited Domains",
        "Dedicated IP (IPv4 + IPv6)",
        "Full Root Access",
        "1 Gbit/s Port",
        "In Built Firewall",
        "Linux/Windows Options"
      ],
      "server": [
        "AMD Ryzen 9 7950X3D (16 Cores)",
        "128 GB RAM",
        "3.84 TB NVMe",
        "Setup Fee: ৳11440",
        "No SSH/Terminal Access"
      ]
    },
    {
      "type": "Dedicated Server",
      "name": "EPYC RAM",
      "period": "monthly",
      "price": 49725,
      "monthlyBreakdown": 49725,
      "currency": "৳",
      "setupFee": 23010,
      "features": [
        "Unlimited Domains",
        "Dedicated IP (IPv4 + IPv6)",
        "Full Root Access",
        "1 Gbit/s Port",
        "In Built Firewall",
        "Linux/Windows Options"
      ],
      "server": [
        "AMD EPYC 9454P (48 Cores)",
        "256 GB RAM",
        "7.68 TB NVMe",
        "Setup Fee: ৳23010",
        "No SSH/Terminal Access"
      ]
    },
    {
      "type": "Dedicated Server",
      "name": "EPYC Storage",
      "period": "monthly",
      "price": 49725,
      "monthlyBreakdown": 49725,
      "currency": "৳",
      "setupFee": 23010,
      "features": [
        "Unlimited Domains",
        "Dedicated IP (IPv4 + IPv6)",
        "Full Root Access",
        "1 Gbit/s Port",
        "In Built Firewall",
        "Linux/Windows Options"
      ],
      "server": [
        "AMD EPYC 9454P (48 Cores)",
        "128 GB RAM",
        "7.68 TB NVMe",
        "Setup Fee: ৳23010",
        "No SSH/Terminal Access"
      ]
    },
    {
      "type": "Dedicated Server",
      "name": "Storage Pro",
      "period": "monthly",
      "price": 26100,
      "monthlyBreakdown": 26100,
      "currency": "৳",
      "setupFee": 11440,
      "features": [
        "Unlimited Domains",
        "Dedicated IP (IPv4 + IPv6)",
        "Full Root Access",
        "1 Gbit/s Port",
        "In Built Firewall",
        "Linux/Windows Options"
      ],
      "server": [
        "AMD Ryzen 7 3700X (8 Cores)",
        "64 GB RAM",
        "88 TB HDD + 2 TB NVMe",
        "Setup Fee: ৳11440",
        "No SSH/Terminal Access"
      ]
    },
    {
      "type": "Dedicated Server",
      "name": "Storage Elite",
      "period": "monthly",
      "price": 51075,
      "monthlyBreakdown": 51075,
      "currency": "৳",
      "setupFee": 23010,
      "features": [
        "Unlimited Domains",
        "Dedicated IP (IPv4 + IPv6)",
        "Full Root Access",
        "1 Gbit/s Port",
        "In Built Firewall",
        "Linux/Windows Options"
      ],
      "server": [
        "AMD Ryzen 9 3900 (12 Cores)",
        "128 GB RAM",
        "176 TB HDD + 3.84 TB NVMe",
        "Setup Fee: ৳23010",
        "No SSH/Terminal Access"
      ]
    },
    {
      "type": "Dedicated Server",
      "name": "Storage Ultimate",
      "period": "monthly",
      "price": 96075,
      "monthlyBreakdown": 96075,
      "currency": "৳",
      "setupFee": 23010,
      "features": [
        "Unlimited Domains",
        "Dedicated IP (IPv4 + IPv6)",
        "Full Root Access",
        "1 Gbit/s Port",
        "In Built Firewall",
        "Linux/Windows Options"
      ],
      "server": [
        "AMD EPYC 7502P (32 Cores)",
        "256 GB RAM",
        "308 TB HDD + 15.36 TB NVMe",
        "Setup Fee: ৳23010",
        "No SSH/Terminal Access"
      ]
    }
  ],
  "domains": [
    {
      "tld": ".com",
      "price": 1650,
      "currency": "৳",
      "period": "yearly"
    },
    {
      "tld": ".net",
      "price": 1750,
      "currency": "৳",
      "period": "yearly"
    },
    {
      "tld": ".org",
      "price": 1650,
      "currency": "৳",
      "period": "yearly"
    },
    {
      "tld": ".io",
      "price": 4500,
      "currency": "৳",
      "period": "yearly"
    },
    {
      "tld": ".co",
      "price": 2850,
      "currency": "৳",
      "period": "yearly"
    },
    {
      "tld": ".me",
      "price": 1950,
      "currency": "৳",
      "period": "yearly"
    },
    {
      "tld": ".info",
      "price": 599,
      "currency": "৳",
      "period": "yearly"
    },
    {
      "tld": ".biz",
      "price": 1450,
      "currency": "৳",
      "period": "yearly"
    },
    {
      "tld": ".club",
      "price": 1150,
      "currency": "৳",
      "period": "yearly"
    }
  ],
  "comparisons": [
    "কম বাজেট থেকে থাকলে Hostfame আর ২৪/৭ এক্সপার্ট সাপোর্ট এবং বেস্ট সার্ভিসের জন্য Hostnin ১০০% রিকমেন্ডেড।",
    "কম প্রাইসে সেরা হোস্টিং এর জন্য Hostfame ভালো হবে। আর বাজেট কিছুটা বাড়াতে পারলে Hostnin বেস্ট হবে।",
    "For a cheaper option, Hostfame is good to start with, but if you prefer something best then Hostnin is 100% recommended.",
    "For affordable performance, go with Hostfame (great for beginners).\nBut if you want premium speed, uptime, and BDIX connectivity, Hostnin is hands down the best choice.\n\nBoth have 24/7 WhatsApp & Live Chat support, so you'll never be stuck.",
    "If you're serious about reliability, I'd say try Hostnin.\n\nIf you're just starting or want budget-friendly US hosting, then Hostfame works perfectly.\n\nBoth are managed by the same experienced team and have amazing support.",
    "You can check Hostnin and Hostfame, both are trusted by a lot of developers here.",
    "ক্লাউড বেইসড হোস্টিং এর ক্ষেত্রে Hostnin রিকমেন্ড করছি। আর ইউজিউয়াল সিপ্যানেল হোস্টিং এ Hostfame ট্রাই করতে পারেন। \n\nতবে যেখান থেকেই নেনকারি কেন, চেক করবেন যে তাদের সাপোর্ট ইন্সট্যান্ট কিনা।",
    "এক্সনহোস্ট ভালো এবং রেপুটেড কোম্পানী। এছাড়া আমি পার্সোনালী এফোর্ডেবল প্রাইসে বেষ্ট সাপোর্টসহ হোষ্টনিন রিকমেন্ড করবো। সিপ্যানেল পার্টনার কোম্পানী, হোষ্টিং ছাড়াও আপনার ওয়েবসাইটের ইন্টারনাল ইস্যুতেও সাপোর্ট পাবেন যা নরমালী অন্যান্য কোম্পানীতে দেওয়া হয় না।",
    "হোস্টিংগার এ রিসেন্টলী ক্যাপচা ইস্যুতে বেশীরভাগ মানুষ বিরক্ত। বাজেট ভালো থাকলে আর আপনার ওয়েবসাইটের ইন্টারনাল সমস্যাসহ যেকোন ইস্যুতে ইন্সট্যান্ট সাপোর্ট পেতে আমি Hostnin রিকমেন্ড করবো।\nসিপ্যানেল পার্টনার আর হোস্টিং এর সাথে এআই ওয়েবসাইট বিল্ডার ফ্রিতে পাবেন।",
    "অনেক হোস্টিং কোম্পানি আছে যারা শুধু হোস্টিং ইস্যুতেই সাপোর্ট দেয়, ওয়েবসাইটের ভিতরে কোনো সমস্যা হলে ডেভেলপারকে দেখাতে বলে। হোস্টনিন এভাবে করে না, আপনার সাইটের ইন্টারনাল ইস্যুতেও হেল্প করবে।",
    "বাংলাদেশের সবচেয়ে কম প্রাইসে .Com ডোমেইন চাইলে হোস্টফেম দেখতে পারেন। আর হোস্টিং নিতে চাইলে হোস্টনিন বেস্ট হবে।",
    "ক্লাউড হোস্টিং চাইলে হোস্টনিন আর ট্র্যাডিশনাল সিপ্যানেল হোস্টিং চাইলে হোস্টফেম দুটোই আমার ব্যক্তিগত রিকমেন্ডেশন।",
    "বাজেটে হোস্টফেম অনেক ভালো। কিন্তু যদি লং টার্ম এ ওয়েবসাইট নিয়ে সিরিয়াস হন তবে হোস্টনিন রিকমেন্ড করবো।",
    "৯৯% সময় মানুষ হোস্টিং চেঞ্জ করে খারাপ সাপোর্টের কারণে, স্পিডের জন্য না। হোস্টনিনে সাপোর্ট নিয়ে কমপ্লেইন করার সুযোগ নেই।",
    "অনেক কোম্পানি প্রথম ইয়ারে ডিস্কাউন্ট দিয়ে পরের বছর ট্রিপল প্রাইস নেয়। হোস্টনিনে এটা হয় না, ফেয়ার প্রাইসিং পলিসি।",
    "আপনার বাজেট কম হলে হোস্টফেম আর বড় হলে হোস্টনিন, দুটোরই সাপোর্ট আর সার্ভিস কোয়ালিটি টপ নচ।",
    "I moved 3 client sites from a popular hosting to Hostnin. Average load time went from 3.2s to 0.8s. The difference is night and day.",
    "Most hosting companies will tell you 'contact your developer' for website issues. Hostnin actually helps you fix internal website problems too.",
    "Most hosting companies offer cheap first-year pricing then double or triple the renewal cost. Hostnin keeps the same price forever.",
    "Budget-friendly? Try Hostfame. Want the absolute best service and support? Go with Hostnin. Both are excellent choices."
  ],
  "policies": {
    "terms_summary": "Introduction, Governing Law & Jurisdiction, Account Registration & Responsibilities, Acceptable Use Policy (AUP), Resource Usage & Fair Usage Policy, Payments, Billing & Refunds, Suspension & Termination, Data Security & Backups, Support & Communication, Domain Registration & Ownership, Service Availability (Uptime SLA), Legal Compliance & Government Requests, Privacy & Data Handling, Limitation of Liability, Indemnification, Account Closure by Customer, Affiliate Program Terms, Domain Registration & Renewal Policy, Content Liability & Copyright Policy (DMCA), Acceptable Email Usage & Anti-Spam Policy, Resource Abuse & Server Security, Backup & Data Restoration Policy, Payment Disputes & Chargebacks, Price Changes & Plan Modifications, Third-Party Services & Licenses, Limitation of Liability (Extended), Indemnification (Extended), Reseller Hosting Terms, Governing Law & Dispute Resolution (Expanded), Service Level Agreement (SLA) Disclaimer, Early Termination & Refund Limitations, Account Ownership & Transfer, Prohibited Content (Explicit List), Severability & Entire Agreement, Changes to Terms, Contact Information, Domain Renewal, Expiry Policy",
    "prohibited": "Adult, spam, nulled scripts, phishing, illegal content.",
    "refund": "30-day money-back guarantee for new hosting. However, refunds to the original payment method are ONLY issued if the issue is our fault (Hostnin's fault). If it is not our fault, the refund will be provided as Account Credit. Domains, VPS, and Dedicated Servers are non-refundable.",
    "affiliate": "20% recurring commission. Minimum payout limit applies.",
    "payment_failure_protocol": "If a customer's card fails (e.g. foreign card error), immediately offer manual bank transfer details. Bank: ISLAMI BANK, Name: SPOTLIGHT CREATIVE, Account Type: Business/Current, BRANCH: PAHARTALI, CHATTOGRAM, ACCOUNT NUMBER: 20502020100506002",
    "vps_info": "VPS Hosting is self-managed by default but full root access is provided. They are available in multiple locations: Bangladesh (BDIX), Singapore, Germany, Finland, and USA. Non-refundable.",
    "dedicated_info": "Dedicated Servers offer maximum performance with fully dedicated hardware. Non-refundable. Most plans have a one-time setup fee (except Value AMD which has Free Setup). Available with Linux/Windows.",
    "domain_fallback": "If a customer asks for a domain extension (.xyz, .ai, .bd, etc.) that is not listed in the pricing list, NEVER say it is not available. Always say: 'Yes, we have it! You can check the real-time availability and exact pricing by searching your domain at https://hostnin.com/domain'."
  },
  "contact": {
    "whatsapp": "+880 1325-875955",
    "website": "https://hostnin.com",
    "email": "support@hostnin.com",
    "payment_bank": "ISLAMI BANK (SPOTLIGHT CREATIVE, Current/Business, Pahartali Branch, Acc: 20502020100506002)"
  },
  "canned_responses": {
    "Greeting": "Hi! Welcome to Hostnin support. How can I help you today?",
    "Please Wait": "Please give me a moment while I look into this for you.",
    "Closing": "Is there anything else I can help you with? Have a great day!",
    "freedomain": "আপনি যদি আমাদের যেকোন ওয়েব হোষ্টিং বা টার্বো হোষ্টিং বা ক্লাউড হোষ্টিং অফার একসাথে ৩ বছরের জন্য বুক করেন, সেক্ষেত্রে ১ম বছরের জন্য ডোমেইন ফ্রী থাকছে। \r\n\r\nফ্রী ডট কম ডোমেইন লিখার পাশে প্রশ্নবোধক আইকনে মাউস হোবার করলে আরো বিস্তারিত তথ্য চেক করতে পারেন পাবেন।",
    "somoi": "সময় দিয়ে সহযোগিতার জন্য আপনাকেও ধন্যবাদ",
    "remote": "https://remotedesktop.google.com/support/\r\n\r\nসরাসরি রিমোট সাপোর্ট দেওয়ার জন্য উপরের লিংকে গিয়ে জেনারেট কোড এ ক্লিক করে কোডটি দিন। \r\n\r\nরিমোট কোড কিভাবে জেনারেট করতে হয় তার বিস্তারিত পাবেন এখানে: https://youtu.be/G_BgDE4_sXI",
    "remoteen": "https://remotedesktop.google.com/support/\r\n\r\nCan you go to this link and Generate the code for us? So we can connect through your Device and guide you on how to do that.\r\n\r\nYou can find detailed instructions on how to generate a remote code here:\r\n\r\nhttps://youtu.be/G_BgDE4_sXI",
    "kidhoroner": "কি ধরনের ওয়েবসাইটের জন্য হোষ্টিং নিতে চাচ্ছেন? আপনার ওয়েবসাইট বা প্রজেক্টের ব্যাপারে জানাতে পারেন যাতে আমব়া আপনার প্রয়োজন অনুযায়ী বেস্ট প্যাকেজটি সাজেস্ট করতে পারি।",
    "visitor": "আপনার ওয়েবসাইটের ভিজিটর কোন কোন দেশ থেকে আসতে পারে? শুধুমাত্র বাংলাদেশ টার্গেট করে হবে নাকি পুরোবিশ্ব?",
    "adrun": "আপনার ওয়েবসাইটকে টার্গেট করে কোন ফেসবুক বা গুগল এড রান করার পরিকল্পনা রয়েছে কি?",
    "showcase": "নাকি শুধুমাত্র শো-কেইস এর জন্য ব্যবহার করতে চাচ্ছেন?",
    "wordpressaddon": "সর্বোচ্চ পারফরম্যান্স নিশ্চিত করার জন্য ম্যানেজ্ড ওয়ার্ডপ্রেস হোস্টিং এ সাবডোমেইন বা এডঅন তৈরী করা যায় না। মাল্টিপল এডঅন বা সাবডোমেইনের জন্য আমরা ক্লাউড হোষ্টিং রিকমেন্ড করছি।",
    "jibolun": "জ্বী বলুন, আপনাকে কিভাবে সহযোগিতা করতে পারি?",
    "gototicket": "This is an automated notification from our system, designed to keep our customers always updated.\r\n\r\nYou can receive support directly from the ticket itself or by replying to the email. Since this process does not fall under our live chat support, we regret that we are unable to provide any further details through live chat.",
    "location": "আমাদের বর্তমানে বিশ্বের প্রায় ৭+ লোকেশনে ডেডিকেটেড সার্ভার রয়েছে। \r\nতন্মোধ্যে উল্লেখযোগ্য হলো: \r\n-Alasaka, USA \r\n-London, UK \r\n-North-Eastern Island, Singapore \r\n-Federated state, Germany \r\n-Dhaka, Bangladesh",
    "Automation": "The message you received is an automated system notification, sent only to inform you that our team has responded to your support ticket.\r\n\r\nThere’s no need to reply to this automated message.\r\nKindly continue your communication through the support ticket.",
    "Web-hosting": "ওয়েব হোষ্টিং এর বিস্তারিত ফিচার্সগুলো দেখতে এই লিংক ভিজিট করুন:\r\n\r\nhttps://hostnin.com/hosting/web-hosting/",
    "transfesr": "এবং আপনার ডোমেইন Hostnin-এ ট্রান্সফার করতে হলে EPP কোড এবং ডোমেইনের রেজিস্ট্রি লক আনলক প্রয়োজন হবে। যদি আপনি EPP কোড বা ডোমেইন আনলকের বিষয়ে না জানেন, তাহলে অনুগ্রহ করে আপনার বর্তমান ডোমেইন কোম্পানির সাথে যোগাযোগ করুন \r\n\r\nট্রান্সফার প্রক্রিয়া শুরু করতে, অনুগ্রহ করে এই লিংক থেকে অর্ডার করুন:\r\nhttps://hostnin.com/transfer",
    "ordering": "আপনি যদি নতুন হয়ে থাকেন এবং অর্ডার করার ব্যাপারে জটিলতা অনুভব করে থাকেন তবে বিস্তারিত গাইডলাইন পাবেন এই ভিডিওতে:\r\nhttps://www.youtube.com/watch?v=RYPkvBzcMcY&t=1s",
    "Ji Obossoi": "জ্বী অবশ্যই।",
    "Demo": "আমাদের ৩০ দিনের গ্যারান্টেড রিফান্ড পলিসি থাকায় স্ক্রিনশট, ট্রায়াল বা কোন ডেমো দেওয়ার প্রয়োজন হয় না।\r\n\r\nহোষ্টিং ক্রয়ের দিন থেকে ৩০ দিন পর্যন্ত আপনি যদি আমাদের কমিটমেন্ট অনুযায়ী সার্ভিস না পেয়ে থাকেন সেক্ষেত্রে আপনি চাইলে ফুল টাকা রিফান্ড ক্লেইম করতে পারবেন\r\n\r\nএছাড়া আমাদের বিস্তারিত রিফান্ড পলিসি পাবেন এই লিংকে: https://hostnin.com/refund-policy",
    "office": "৮ম তলা, প্রশান্তি আবাসিক এলাকা গেইট সংলগ্ন, ডি.টি. রোড, কর্নেলহাট, চট্টগ্রাম। \r\n\r\nঅফিস পথ নির্দেশিকা: চট্টগ্রাম শহরের সিটি গেইট থেকে আগে এবং এ.কে খান এর মধ্যবর্তী স্থানে কর্ণেলহাট এ আমাদের অফিস অবস্থিত। এছাড়া আমাদের USA এর Wyoming State এও অফিস রয়েছে।",
    "Freedomain": "আপনি যদি আমাদের যেকোন  ওয়েব হোষ্টিং বা টার্বো হোষ্টিং বা ক্লাউড হোষ্টিং অফার একসাথে ৩ বছরের জন্য বুক করেন, সেক্ষেত্রে ১ম বছরের জন্য ডোমেইন ফ্রী থাকছে।\r\nআপনি ফ্রী ডট কম ডোমেইন লিখার পাশে প্রশ্নবোধক আইকনে মাউস হোবার করলে ডিটেইলস দেখতে পাবেন।",
    "ticket": "যেকোন টেকনিক্যাল ইস্যুতে আমাদের সাপোর্ট এ জানালে আমাদের টিম ১৫ মিনিট বা তার কম সময়ে সেটি সমাধান করেন। দ্রুত সাপোর্ট নিশ্চিত করতে অনুগ্রহপুর্বক এই লিংক থেকে আপনার ইস্যুটি সাবমিট করুন: hostnin.com/support \r\n\r\nএছাড়া সরাসরি মেইল করলে বা সেখানে রিপ্লাই করলেও আমাদের টিম এটি রিসিভ করবেন। সরাসরি মেইল করতে ব্যবহার করুন support@hostnin.com\r\n\r\nকিভাবে টিকিট ওপেন করতে হয় তার বিস্তারিত পাবেন এই লিংকে::\r\nhttps://youtu.be/eNgZfXg_USI",
    "koto": "কি ধরনের ওয়েবসাইটের জন্য হোষ্টিং নিতে চাচ্ছেন? আপনার ওয়েবসাইট বা প্রজেক্টের ব্যাপারে জানাতে পারেন যাতে আমি আপনার প্রয়োজন অনুযায়ী বেস্ট প্যাকেজটি সাজেস্ট করতে পারি।",
    "ads": "আপনার ওয়েবসাইটকে টার্গেট করে কোন ফেসবুক বা গুগল এড রান করার পরিকল্পনা রয়েছে কি? নাকি শুধুমাত্র শো-কেইস এর জন্য ব্যবহার করতে চাচ্ছেন?",
    "domainlink": "অনুগ্রহপুর্বক আপনার ডোমেইন লিংকটি দিন যাতে আমি চেক করতে পারি।",
    "check-ing": "আপনার ইস্যুটি আমি চেক করছি। আশা করছি খুব দ্রুতই আমরা আপনাকে আপডেট জানাতে পারবো। সময় দিয়ে সহযোগিতার জন্য ধন্যবাদ।",
    "sure": "Sure, how can we help you?",
    "Bank-transfer": "You can pay with credit and debit cards (Visa, Mastercard, American Express), digital wallets (Apple Pay, Google Pay), bank transfers.",
    "ticketen": "For technical issues our team is here to help and typically resolves most problems in 15 minutes or less.\r\n\r\nFor the fastest support, please submit your request here:\r\n👉 hostnin.com/support\r\n\r\nYou can also reach us directly via email at support@hostnin.com.",
    "offeren": "In our ongoing Black Friday Offer, you can get up to 70% off on Web, BDIX, or Turbo Hosting plans!\r\n\r\nPlus, when you book for 3 years together, you’ll receive a free .COM domain with your purchase.\r\n\r\nFor more details, visit:\r\n👉 https://hostnin.com/hosting/web-hosting",
    "basic": "বর্তমান অফারে ১০ জিবি ক্লাউড বেসিক প্যাকেজ ইয়ারলী ৯৯৯ টাকা। \r\n\r\n৩ বছরের জন্য বুক করলে সাথে ফ্রি ডোমেইন থাকছে প্রথম বছরের জন্য। ৩ বছরের জন্য ৩x৯৯৯ = ২৯৯৭ টাকা আসবে। সাথে প্রথম বছব়েব় জন্য .COM ডোমেইন সম্পুর্ণ ফ্রি। \r\n\r\nবিস্তারিত ফিচার্সগুলো দেখতে ভিজিট করুন: https://hostnin.com/hosting/cloud-hosting/",
    "done": "সময় দিয়ে সহযোগিতার জন্য ধন্যবাদ, আমি আপনার জন্য এটি করে দিয়েছি।",
    "estimatetraffic": "ওয়েবসাইট কতজন ভিজিটর নিতে পারবে, সেটা নির্ভর করে সার্ভারের CPU, RAM, I/O স্পিড আর Entry Process-এর ওপর। সহজভাবে বললে, CPU ও RAM যত বেশি, সার্ভার তত দ্রুত রিকোয়েস্ট প্রোসেস করতে পারে। \r\n\r\nI/O স্পিড ঠিক করে কত দ্রুত ডেটা পড়া, লেখা হবে, আর Entry Process বলে দেয় একসাথে কতজন ভিজিটর সাইটে ঢুকতে পারবে। তাই ভালো রিসোর্স মানে বেশি ট্রাফিক হ্যান্ডেল করার ক্যাপাসিটি সাইট অপটিমাইজ থাকলে দিনে কয়েক হাজার থেকে কয়েক লাখ ভিজিটরও ম্যানেজ করা সম্ভব।\r\n\r\nধরুন আপনি আমাদের ওয়েব হোস্টিং আল্টিমেট প্ল্যানটি ব্যবহার করছেন যাতে 4 Core CPU, 4 GB RAM, 35 Mbps I/O Speed আর 80 Entry Process ইনক্লুডেড রয়েছে। এই রিসোর্স মানে সার্ভার একসাথে অনেক রিকোয়েস্ট দ্রুত প্রোসেস করতে পারে এবং ৮০ জন পর্যন্ত ভিজিটর একই সময়ে ওয়েবসাইটে থাকতে পারবে কোনো স্পিড ড্রপ ছাড়া। এই ৮০ জন কোন ধরনের অপটিমাইজেশন করার আগের মেট্রিক্স তবে আমাদের সার্ভার যেহেতু ফুলী অপটিমাইজড এক্ষেত্রে এই কনফিগারেশনে প্রতিদিন ১৫–৩০ হাজার ভিজিটর অনায়াসে হ্যান্ডেল করা যাবে। \r\n\r\nCPU নির্ধারণ করে সার্ভার একসাথে কত ভিজিটরের রিকোয়েস্ট প্রসেস করতে পারবে, আর RAM নির্ধারণ করে সেই রিকোয়েস্টগুলো কতটা মেমরিতে ধরে রাখা যাবে। বেশি CPU মানে দ্রুত প্রসেসিং, বেশি RAM মানে একসাথে বেশি ভিজিটর হ্যান্ডেল করা। যেমন ৪ কোর CPU আর ৪GB RAM থাকলে অপটিমাইজ করা সাইট সহজে একসাথে ৭০–১২০ ভিজিটর আর দিনে ২০–৩০ হাজার ভিজিটর কোন সমস্যা ছাড়াই ম্যানেজ করতে পারে।",
    "googlesearchconsole": "ডোমেইনের সাথে কিভাবে গুগল সার্চ কনসোল বা ব্লগার এড করবেন এখানে বিস্তারিত পাবেন:\r\n\r\nhttps://youtu.be/jWlfgXgCaqA",
    "blogger": "ডোমেইনের সাথে কিভাবে গুগল সার্চ কনসোল বা ব্লগার এড করবেন এখানে বিস্তারিত পাবেন:\r\n\r\nhttps://youtu.be/jWlfgXgCaqA",
    "domain-transfer": "ডোমেইন ট্রান্সফার করার জন্য আপনার ডোমেইন এর ইপিপি কোড সংগ্রহ করতে হবে এবং এটির রেজিষ্ট্রি লক আনলক করতে হবে। এরপর এই লিংক থেকে ট্রান্সফার অর্ডার করতে পারবেন:\r\n\r\nhttps://hostnin.com/domain",
    "wordpressinstall": "সিপ্যানেলে ওয়ার্ডপ্রেস কিভাবে ইনষ্টল বা আনইনষ্টল করবেন তার বিস্তারিত পাবেন এখানে: https://youtu.be/lhg8dXfXoVU",
    "control-paneladdon": "কন্ট্রোল প্যানেলে কিভাবে অ্যাডঅন ডোমেইন অ্যাড করতে পারবেন, তা বিস্তারিত পাবেন এখানে: https://youtu.be/Ot8NeTxqAx8?si=IM7GHwVfOnQkBTFO",
    "products": "ওয়েবসাইটে পাবলিশ করার জন্য বর্তমানে প্রোডাক্ট সংখ্যা কেমন রয়েছে? এবং আগামী ৬ মাসে কি পরিমাণ প্রোডাক্ট আপলোড হতে পারে?",
    "webpro": "এক্ষেত্রে আপনার ই-কমার্স ওয়েবসাইটের স্মুথ পারফরম্যান্সের জন্য ওয়েব হোষ্টিং প্রো প্যাকেজটি রিকমেন্ড করছি।",
    "fast": "সুপার ফাষ্ট স্পীডের জন্য এই সার্ভারে ব্যবহার করা হয়েছে 16 ডেডিকেটেড Core ও 192GB DDR5 RAM এর NVMe সার্ভার স্টোরেজ যা বাংলাদেশ সহ যেকোনো লোকেশেন থেকে সুপার ফাষ্ট স্পীড নিশ্চিত করে থাকে।",
    "webfeature": "ওয়েব হোষ্টিং এর বিস্তারিত ফিচার্সগুলো দেখতে এই লিংক ভিজিট করুন: https://hostnin.com/hosting/web-hosting/",
    "bujhte": "আন্তরিকভাবে দু:খিত যে আমি বিষয়টি বুঝতে পারিনি। আপনি কি আরেকটু ব্যাখা করতে পারেন?",
    "vps": "আমাদের ভিপিএস এর প্রাইসিংগুলো পাবেন এই লিংকে: https://hostnin.com/hosting/vps-hosting",
    "dedi": "এবং ডেডিকেটেড এর প্রাইসিং পাবেন এই লিংকে: https://hostnin.com/hosting/dedicated-server",
    "vpsen": "Check out our VPS hosting plans here: https://hostnin.com/hosting/vps-hosting",
    "emails": "আপনার কাছে প্রেরিত সকল ইমেইল এক জায়গায় দেখতে এই লিংকটি ভিজিট করুন: https://my.hostnin.com/clientarea.php?action=emails",
    "login": "আপনার লগিন ইনফরমেশনসহ যাবতীয় একসেস আপনাকে ইমেইল করা হয়েছে। কোন কারণে আপনার ইমেইলের প্রাইমারী ফোল্ডারে না পেলে অনুগ্রহপূর্বক স্প্যাম ফোল্ডার চেক করুন। লগিন ইনফরমেশন ইমেইলে কন্ট্রোল প্যানেলে লগিন করার ইউজারনেম এবং পাসোয়ার্ড পাবেন।",
    "orderingen": "If you are new and feeling complexity while ordering, check out this video for detailed guidance:\r\nhttps://www.youtube.com/watch?v=RYPkvBzcMcY&t=1s\r\n\r\n\r\nYou can also register using your information so we can order from your account and give you a direct payment link.\r\n\r\nUse this link for registration:\r\nhttps://my.hostnin.com/register.php",
    "call": "প্রিয় গ্রাহক, আমাদের সাথে যোগাযোগ এর প্রচেষ্টার জন্য ধন্যবাদ। আপনাকে কিছু সময়ের মধ্যেই আমাদের হটলাইন থেকে কলব্যাক করা হবে। \r\n\r\nভবিষ্যতে যেকোন সময় কল সাপোর্ট পেতে অনুগ্রহপূর্বক \"Call Support\" লিখে মেসেজ করলে আমাদের একজন সাপোর্ট এজেন্ট আপনাকে কলব্যাক করবেন।\r\n\r\nএছাড়া ২৪ ঘন্টা যেকোন সময় ইন্সট্যান্ট কল সাপোর্ট পেতে ব্যবহার করুন:\r\n09617875955\r\n\r\nউল্লেখ্য যে, ফিউচার রেকর্ড, ট্রান্সপারেন্সী ও টিম ট্রেইনিং এর জন্য আপনার প্রতিটি কল রেকর্ড করা হয়ে থাকে ।",
    "development": "ওয়েবসাইট ডেভেলপমেন্ট মূলত বিভিন্ন বিষয়ের উপর নির্ভর করে, যেমন ডিজাইন, প্রয়োজনীয় ফিচার, ও থার্ড-পার্টি ইন্টিগ্রেশন।\r\nআপনার প্রজেক্টের চাহিদা অনুযায়ী সঠিক প্ল্যান ও বাজেট নির্ধারণ করতে হলে বিস্তারিতভাবে আলোচনা করা প্রয়োজন।\r\n\r\nআমাদের ডেভেলপমেন্ট টিম এই বিষয়ে আপনাকে পূর্ণ সহায়তা করবে।\r\n\r\nআপনি চাইলে এ বিষয়ে বিস্তারিত আলোচনা করার জন্য সম্পুর্ণ ফ্রিতে ডেভেলপমেন্ট টিমের সাথে একটি মিটিং বুক করতে পারেন:\r\nhttps://hostnin.com/book-consultation",
    "ji": "জ্বী বলুন, আপনাকে কিভাবে সহযোগিতা করতে পারি?",
    "demo": "আমাদের ৩০ দিনের প্রশ্ন ছাড়া গ্যারান্টেড রিফান্ড পলিসি থাকায় স্ক্রিনশট, ট্রায়াল বা কোন ডেমো দেওয়ার প্রয়োজন হয়বিধা নেই।\r\n\r\nহোষ্টিং ক্রয়ের দিন থেকে ৩০ দিন পর্যন্ত আপনি যদি মনে করেন যে এটি আপনার জন্য প্রযোজ্য নয় তবে কোন প্রশ্নের উত্তর দেওয়া ছাড়া পুরো টাকা রিফান্ড নিতে পারবেন।",
    "recommendationturboultimate": "এক্ষেত্রে আপনার ওয়েবসাইটের জন্য টার্বো হোষ্টিং আল্টিমেট প্যাকেজটি রিকমেন্ড করছি।\r\n\r\nসুপার ফাষ্ট স্পীডের জন্য এই সার্ভারে ব্যবহার করা হয়েছে 16 ডেডিকেটেড Core ও 192GB DDR5 RAM এর NVMe সার্ভার স্টোরেজ যা বাংলাদেশ এর যেকোনো লোকেশেন থেকে ১ সেকেন্ডের মধ্যে গ্যারান্টেড স্পীড নিশ্চিত করে থাকে। \r\n\r\nআমাদের টার্বো হোষ্টিং এর আল্টিমেট প্ল্যানটি ফেইসবুক এডভিত্তিক ই-কমার্স ওয়েবসাইটের জন্য বিশেষভাবে তৈরী।",
    "screen": "কি ধরনের সমস্যা পাচ্ছেন সেটির একটি স্ক্রিনশট দিলে আমরা আপনার সমস্যাটি বুঝতে পারবো এবং সে অনুযায়ী সল্যুশন দিতে পারবো।",
    "ipserver": "আমাদের অনেক সার্ভার থাকায় নির্দিষ্ট কোন আইপি দেওয়া এবং সিক্যুরিটি ইস্যুতে সরাসরি আইপি দেওয়া সম্ভব হয় না। তবে কেনার পর আপনি চাইলে নিজেই চেক করতে পারবেন। শুধুমাত্র গ্রাহকদের জন্য আইপি সংক্রান্ত যেকোন তথ্য প্রদান করা হয়।",
    "cloudnameserver": "আমাদের ক্লাউড নেমসার্ভারগুলোঃ \r\nns1.stackdns.com\r\nns2.stackdns.com\r\nns3.stackdns.com\r\nns4.stackdns.com",
    "migrationen": "If you currently have a website hosted elsewhere and want to migrate it to us, you need to order the Migration Pro service.\r\n\r\nOur team of experts will complete the migration without losing a single file on your hosting. Migration includes all the files, databases, and emails.",
    "migrationbn": "আপনার যদি বর্তমানে অন্য কোথাও ওয়েবসাইট হোস্ট করা থাকে এবং সেটি আমাদের এখানে মাইগ্রেট করতে চান তবে Migration Pro সার্ভিসটি অর্ডার করতে হবে।\r\n\r\nএছাড়া আপনি যদি একজন ওয়েবসাইট এক্সপার্ট বা ডেভেলপার হোন তবে খুব সহজেই নিজেই মাইগ্রেশন করতে পারবেন।",
    "welcome": "You’re most welcome! If you need any further assistance, please don’t hesitate to let us know. We’re always here to help.",
    "cloudemail": "আমাদের ক্লাউড হোস্টিং আলটিমেট প্যাকেজে ডিফল্টভাবে প্রফেশনাল ইমেইল সুবিধা আছে। অর্থাৎ, আপনি সহজেই নিজের ডোমেইন নেম ব্যবহার করে বিজনেস ইমেইল অ্যাকাউন্ট তৈরি ও পরিচালনা করতে পারবেন, কোনো অতিরিক্ত সেটআপ ছাড়াই। প্যাকেজটিতে IMAP, POP3 এবং SMTP-এর মতো প্রয়োজনীয় ইমেইল প্রোটোকল সাপোর্ট করে, যা আপনার ইমেইল ব্যবস্থাপনাকে আরও দ্রুত, নির্ভরযোগ্য ও সিকিউর করে তোলে।\r\n\r\nOur Cloud Hosting Ultimate package includes built-in professional email features by default. This means you can easily create and manage business email accounts using your own domain name without needing any external setup. The package supports essential email protocols like IMAP, POP3, and SMTP, ensuring smooth and secure email delivery.\r\n\r\nক্লাউড হোষ্টিং আলটিমেট প্যাকেজের বিস্তারিত ফিচার্সগুলো দেখতে এই লিংক ভিজিট করুন: https://hostnin.com/hosting/cloud-hosting",
    "traffic": "ওয়েবসাইট কতজন ভিজিটর নিতে পারবে, সেটা নির্ভর করে সার্ভারের CPU, RAM, I/O স্পিড আর Entry Process-এর ওপর। সহজভাবে বললে, CPU ও RAM যত বেশি, সার্ভার তত দ্রুত রিকোয়েস্ট প্রোসেস করতে পারে। \r\n\r\nI/O স্পিড ঠিক করে কত দ্রুত ডেটা পড়া, লেখা হবে, আর Entry Process বলে দেয় একসাথে কতজন ভিজিটর সাইটে ঢুকতে পারবে। তাই ভালো রিসোর্স মানে বেশি ট্রাফিক হ্যান্ডেল করার ক্যাপাসিটি সাইট অপটিমাইজ থাকলে দিনে কয়েক হাজার থেকে কয়েক লাখ ভিজিটরও ম্যানেজ করা সম্ভব।\r\n\r\nধরুন আপনি আমাদের ওয়েব হোস্টিং আল্টিমেট প্ল্যানটি ব্যবহার করছেন যাতে 4 Core CPU, 4 GB RAM, 35 Mbps I/O Speed আর 80 Entry Process ইনক্লুডেড রয়েছে। এই রিসোর্স মানে সার্ভার একসাথে অনেক রিকোয়েস্ট দ্রুত প্রোসেস করতে পারে এবং ৮০ জন পর্যন্ত ভিজিটর একই সময়ে ওয়েবসাইটে থাকতে পারবে কোনো স্পিড ড্রপ ছাড়া। এই ৮০ জন কোন ধরনের অপটিমাইজেশন করার আগের মেট্রিক্স তবে আমাদের সার্ভার যেহেতু ফুলী অপটিমাইজড এক্ষেত্রে এই কনফিগারেশনে প্রতিদিন ১৫–৩০ হাজার ভিজিটর অনায়াসে হ্যান্ডেল করা যাবে। \r\n\r\nCPU নির্ধারণ করে সার্ভার একসাথে কত ভিজিটরের রিকোয়েস্ট প্রসেস করতে পারবে, আর RAM নির্ধারণ করে সেই রিকোয়েস্টগুলো কতটা মেমরিতে ধরে রাখা যাবে। বেশি CPU মানে দ্রুত প্রসেসিং, বেশি RAM মানে একসাথে বেশি ভিজিটর হ্যান্ডেল করা। যেমন ৪ কোর CPU আর ৪GB RAM থাকলে অপটিমাইজ করা সাইট সহজে একসাথে ৭০–১২০ ভিজিটর আর দিনে ২০–৩০ হাজার ভিজিটর কোন সমস্যা ছাড়াই ম্যানেজ করতে পারে।",
    "developHostfame": "ওয়েবসাইট ডেভেলপমেন্ট মূলত বিভিন্ন বিষয়ের উপর নির্ভর করে, যেমন ডিজাইন, প্রয়োজনীয় ফিচার, ও থার্ড-পার্টি ইন্টিগ্রেশন। আপনার প্রজেক্টের চাহিদা অনুযায়ী সঠিক প্ল্যান ও বাজেট নির্ধারণ করতে হলে বিস্তারিতভাবে আলোচনা করা প্রয়োজন। আমাদের ডেভেলপমেন্ট টিম এই বিষয়ে আপনাকে পূর্ণ সহায়তা করবে। আপনি চাইলে এ বিষয়ে বিস্তারিত আলোচনা করার জন্য সম্পুর্ণ ফ্রিতে ডেভেলপমেন্ট টিমের সাথে একটি মিটিং বুক করতে পারেন: https://tidycal.com/screative/hostfame",
    "wordpressunistall": "কিভাবে ওয়ার্ডপ্রেস আনইনষ্টল করবেন তা দেখতে এই ভিডিওটি দেখুন:\r\n\r\nhttps://youtu.be/WfSqp1Hfn7Y",
    "manuall": "Login Control Panel: my.hostnin.uk\r\n\r\nUsername: your email address\r\nPassword: your password\r\n\r\nTo reset your password visit this link:\r\nmy.hostnin.uk/recover",
    "livechat": "কিভাবে মেসেজের মাধমে টিকিট ওপেন করতে হয় তার বিস্তারিত পাবেন এই লিংকে::\r\nhttps://youtu.be/BUU6-Mkv5WA\r\n\r\nসরাসরি লাইভচ্যাট এ মেসেজ করে টিকিট ওপেন করতে এই লিংকে ক্লিক করুন বা এটাচমেন্টে যুক্ত হওযা QR কোড স্ক্যান করেও লাইভচ্যাট একসেস করতে পারবেন:\r\n\r\nhttps://api.talkfuze.com/uw/embed/c08cad93-cc21-390e-901a-c4e3263d3748",
    "discounts": "No further discount is necessary since we are already offering this at a significant discount.\r\n\r\nHowever, you can unlock even more savings by opting for a longer billing period. With a 3-year plan, you’ll receive a domain completely free for the first year.",
    "mahmudul": "হোষ্টনিন সাপোর্ট থেকে মাহমুদুল আছি আপনার সাথে, আপনাকে আজ কিভাবে সহযোগিতা করতে পারি?",
    "registry": "আমরা বিভিন্ন রেজিষ্ট্রির সাথে পার্টনারশিপের মাধ্যমে ডোমেইন প্রোভাইড করি থাকি। আমাদের সাথে পার্টনারশিপে থাকা কোম্পানীগুলোর মধ্যে উল্লেখযোগ্য হলো:\r\n\r\n►নেমসিলো\r\n►পাবলিক ডোমেইন রেজিষ্ট্রি\r\n►ইনোম\r\n►কসমোটাউন\r\n►রিসেলারক্লাব",
    "whatsapp": "সরাসরি হোয়াটসঅ্যাপ সাপোর্ট এর জন্য অনুগ্রহপূর্বক নীচের লিংক থেকে মেসেজ করুন। https://wa.me/message/ZNJHDTKIRBRKD1",
    "cloudflare": "You can find a detailed guide on how to add a domain to Cloudflare and add DNS records in this video:\r\n\r\nhttps://www.youtube.com/watch?v=QSXPPJZdCpk&t=8s\r\n\r\nThe video provides step-by-step instructions to help you easily add your domain to Cloudflare and manage DNS records effectively.",
    "review": "আপনি যদি আমাদের সার্ভিস ও সাপোর্টে সন্তুষ্ট হয়ে থাকেন তবে আমাদেরকে রিভিউ দেওয়ার মাধ্যমে আরো ভালো সাপোর্ট ও সার্ভিস নিশ্চিত করার জন্য এগিয়ে যেতে সহযোগিতা করতে পারেন। এতে আমাদের নতুন গ্রাহকরা আমাদের সেবা নিতে উৎসাহ পাবেন এবং এর মাধ্যমে আমরা আরো শক্তিশালী কোম্পানী হিসেবে আমাদের সার্ভিস এবং সাপোর্টের মান উন্নয়ন করতে পারবো।\r\n\r\nরিভিউ দেওয়ার জন্য এই দুইটি লিংক ব্যবহার করতে পারবেন:\r\n\r\n১) https://g.page/r/CWkkbwnR-g3qEBM/review\r\n\r\n২) https://www.trustpilot.com/review/hostnin.com",
    "discount": "বর্তমানে সর্বোচ্চ ডিসকাউন্ট থাকায় অতিরিক্ত কোন ছাড় দেওয়া যাচ্ছে না বলে আমরা আন্তরিকভাবে দু:খিত।",
    "checking": "ধন্যবাদ, আমি বিষয়টি চেক করছি এবং খুব দ্রুতই এই ব্যাপারে আপডেট পাবেন।\r\n\r\nসময় দিয়ে সহযোগিতার জন্য আন্তরিকভাবে ধন্যবাদ।",
    "dns": "When a domain nameserver is updated, it may take up to 24 hours for the change to take effect. This period is called DNS propagation.\r\n\r\nIn other words, it is a period ISP (Internet service provider) nodes across the world take to update their caches with the new DNS information of your domain. Usually, it happens within 1 hour or so.\r\n\r\nYou can check the DNS propagation status:\r\nhttps://dnschecker.org/",
    "stackdns": "ns1.stackdns.com\r\nns2.stackdns.com\r\nns3.stackdns.com\r\nns4.stackdns.com",
    "specific": "Make it specific",
    "visitoren": "Where do you want your website visitors to come from only Bangladesh, or from around the world?",
    "adsen": "Do you plan to run any Facebook or Google ads targeting your website, or are you planning to use it only for showcasing purposes?",
    "Bye": "If you need any further assistance, please don’t hesitate to reach out. I’ll be happy to help.",
    "sharedomain": "Could you please share your domain address?",
    "service": "জ্বী , আমরা ডোমেইন ও হোস্টিং সেবা প্রদান করে থাকি, পাশাপাশি আমাদের একটি ডেডিকেটেড ডেভেলপমেন্ট টিম রয়েছে, যেখানে থেকে আপনি ডেভেলপমেন্ট সার্ভিসও নিতে পারবেন।",
    "epptransfer": "To transfer your domain to hostnin, you need an EPP code and a registry lock unlocked of the domain. If you don't know about the EPP code or Unlocking the domain; please contact your current domain company or share the current company website access so we can contact on your behalf you.\r\n\r\nTo process the transfer, please order from this link: https://my.hostnin.com/cart.php?a=add&domain=transfer",
    "callen": "For instant call support at any time, 24/7, please contact:\r\n09617875955\r\n\r\nPlease note that all calls are recorded for future reference, transparency, and team training purposes.",
    "hostfamedevelopment": "ওয়েবসাইট ডেভেলপমেন্ট মূলত বিভিন্ন বিষয়ের উপর নির্ভর করে, যেমন ডিজাইন, প্রয়োজনীয় ফিচার, ও থার্ড-পার্টি ইন্টিগ্রেশন।\r\nআপনার প্রজেক্টের চাহিদা অনুযায়ী সঠিক প্ল্যান ও বাজেট নির্ধারণ করতে হলে বিস্তারিতভাবে আলোচনা করা প্রয়োজন।\r\n\r\nআমাদের ডেভেলপমেন্ট টিম এই বিষয়ে আপনাকে পূর্ণ সহায়তা করবে।\r\n\r\nআপনি চাইলে এ বিষয়ে বিস্তারিত আলোচনা করার জন্য সম্পুর্ণ ফ্রিতে ডেভেলপমেন্ট টিমের সাথে একটি মিটিং বুক করতে পারেন:\r\nhttps://tidycal.com/screative/",
    "ami": "আমি কি আর কোন তথ্য দিয়ে সহযোগিতা করতে পারি?",
    "is": "Is there anything else i can help you with?",
    "pack": "প্রিয় গ্রাহক, আমি কি জানতে পারি আপনি আমাদের কোন হোষ্টিং প্যাকেজটি ব্যবহার করছেন?",
    "Koto": "আপনি কি ধরনের ওয়েবসাইটের জন্য হোস্টিং নিতে চাচ্ছেন?",
    "turboultimatelink": "টার্বো হোষ্টিং আল্টিমেট এর বিস্তারিত ফিচার্স ও প্রাইসিংগুলো পাবেন এই লিংকে: https://hostnin.com/hosting/turbo-hosting",
    "any": "If you have any further questions, I'm here to assist you.",
    "sslcpanel": "সিপ্যানেলে এসএসএল একটিভ করার জন্য এই ভিডিওটি আপনাকে সহযোগিতা করবে: https://www.youtube.com/watch?v=5LdMVBMSxE4",
    "webhosting": "এক্ষেত্রে আপনার ই-কমার্স ওয়েবসাইটের স্মুথ পারফরম্যান্সের জন্য ওয়েব হোষ্টিং স্টার্টার প্যাকেজটি রিকমেন্ড করছি। প্যাকেজটির \r\nসাথে আপনি একটি .Com ডোমেইন ফ্রি পাচ্ছেন এক বছর এর জন্য যার রেগুলার প্রাইস ১৬৫০ টাকা।\r\n\r\nওয়েব হোষ্টিং স্টার্টার এর বিস্তারিত ফিচার্সগুলো দেখতে এই লিংক ভিজিট করুন: https://hostnin.com/hosting/web-hosting/",
    "tools": "এছাড়া ওয়েব হোষ্টিং স্টার্টার প্যাকেজের সাথে ২০টির বেশী এসইও ওয়েবসাইট অপটিমাইজেশন টুলস সম্পুর্ন ফ্রি রয়েছে।",
    "velocityrestore": "Dear Customer,\r\n\r\nWe have identified some internal network connectivity issues on your current server. Our technical team is actively working to resolve the matter. To ensure uninterrupted service and improved performance, we are migrating your account to a different server.\r\n\r\nWe kindly request your patience and cooperation during this process.\r\n\r\nIn addition, please update your domain with the following nameservers:\r\n\r\nsparkone.balancedserver.com\r\nsparktwo.balancedserver.com\r\n\r\nThank you for your patience, we’ll bring everything back online as quickly as possible.",
    "walaikum": "ওয়ালাইকুম আসসালাম",
    "obossoi": "জ্বী অবশ্যই।",
    "webproprice": "Currently, our Web Hosting Pro plan is priced at ৳249 per month, with same-price renewal guaranteed.\r\n\r\nThe 3-year billing option costs ৳8,964 in total, which locks your price for the next three years and protects you from future price increases.\r\n\r\nFor more details about this plan's features, you can visit:\r\nhttps://hostnin.com/hosting/web-hosting",
    "critical": "আপনার সহযোগিতার জন্য ধন্যবাদ। এটি ওয়ার্ডপ্রেসে ক্রিটিক্যাল ইরর সাধারণত কোনো ম্যালফাংশনিং প্লাগিন, স্ক্রিপ্ট, বা কোডের কারণে ঘটে যার ফলে এরকমটি দেখায়। যেহেতু সমস্যাটি হোস্টিং বা ডোমেইন সমস্যার সাথে সম্পর্কিত নয়, তাই আমরা এ বিষয়ে বিস্তারিত সহায়তা প্রদান করতে পারছি না। এই সমস্যাটি বোঝার এবং সমাধান করার জন্য আমরা আপনাকে এই আর্টিকেলটি পড়ার পরামর্শ দিচ্ছি: https://rankmath.com/blog/fix-wordpress-critical-error এছাড়া সমস্যাটি সমাধানে আপনি এই ভিডিওটি দেখতে পারেন: https://guide.hostnin.com/recordings/hihR3WGfQGs94eirP0P0",
    "cpaneladdon": "সিপ্যানেলে এডঅন ডোমেইন এড করার ব্যাপারে বিস্তারিত দেখতে এই ভিডিওটি আপনাকে সহযোগিতা করবে:\r\n\r\nhttps://www.youtube.com/watch?v=gAupgQFHkaM&t=7s",
    "cpanelssl": "Watch this video to active SSL Certificate: https://www.youtube.com/watch?v=5LdMVBMSxE4",
    "activessl": "Watch this video to active SSL Certificate: https://www.youtube.com/watch?v=5LdMVBMSxE4",
    "bkash": "01325875955 - (Bkash, Nagad, Rocket, Cellfin & Upay)",
    "wordpresscpanel": "সিপ্যানেলে ওয়ার্ডপ্রেস কিভাবে ইনষ্টল বা আনইনষ্টল করবেন তার বিস্তারিত পাবেন এখানে: \r\nhttps://youtu.be/lhg8dXfXoVU",
    "how": "To recommend the best plan for you, can I ask a couple of quick questions about your site? Like, what kind of products or services are you selling, and how many visitors do you usually get?",
    "adspend": "আপনার প্রতিদিন কত ডলার বাজেট এড স্পেন্ড করার প্ল্যান রয়েছে?",
    "cloudflarebn": "কিভাবে ডোমেইনকে ক্লাউডফ্লেয়ারে এড করে ডিএনএস রেকর্ড এড করতে হয় তার বিস্তারিত গাইড পাবেন এই ভিডিওতে:\r\n\r\nhttps://www.youtube.com/watch?v=QSXPPJZdCpk&t=8s",
    "bankaccount": "Bank: ISLAMI BANK \r\nName: SPOTLIGHT CREATIVE\r\nAccount Type: Business/Current\r\nBRANCH: PAHARTALI, CHATTOGRAM\r\nACCOUNT NUMBER:20502020100506002",
    "domainorder": "আপনি ডোমেইন অর্ডার করতে চাইলে এই লিংকে প্রবেশ করুন: \r\n\r\nhttps://hostnin.com/domain/",
    "hello": "Hello, How can i help you?",
    "expensive": "আমরা সুপার ফাষ্ট এন্টারপ্রাইজ গ্রেডের সার্ভার ও ২৪ ঘন্টা নিরবিচ্ছিন্ন এক্সপার্ট সাপোর্ট দিয়ে থাকি যার ফলে আমাদের প্রাইসগুলো অন্যান কম দামী প্যাকেজ থেকে কিছুটা বেশী মনে হতে পারে। তবে আপনি যদি আমাদের সার্ভিস এবং সাপোর্ট নিয়ে থাকেন সেক্ষেত্রে খুব সহজেই বুঝতে পারবেন যে আমাদের সার্ভিস ও সাপোর্টের কোয়ালিটি অনুযায়ী আমাদের প্রাইসগুলো খুবই এফোর্ডেবল।\r\n\r\nএছাড়া আপনার কাছে যদি মনে হয় যে একই মানের সার্ভিস ও সাপোর্ট কোয়ালিটিসহ অন্য কোম্পানী এর থেকে কম প্রাইসে অফার করছে তবে সেখান থেকে  ট্রাই করতে পারেন, সেখানে যদি আপনার প্রয়োজন পুরণ না হয় তবে ভবিষ্যতে যেকোনো সময় আমাদের সার্ভিস নিতে পারবেন।",
    "screenen": "Please share a screenshot of your issue so we can understand it better and be able to provide a proper solution for that.",
    "nameserver": "ডোমেইনে নেমসার্ভার আপডেট করার প্রসেস দেখতে এই ভিডিওটি ফলো করুন: https://www.youtube.com/watch?v=bMeG3lbcH2s&t=4s",
    "happy": "Happy to help!",
    "cloudandweb": "Since the cloud hosting server is UK-based, it may perform slightly slower from Bangladesh. However, it is especially suitable for websites targeting users in the UK and the USA.\r\n\r\nOn the other hand, Web hosting is based on global servers, which provide good performance both in Bangladesh and worldwide. In addition, due to advanced features, high resources, and stable servers, we recommend Web hosting for websites with visitors from Bangladesh as well as global audiences.",
    "duplicate": "প্রিয় গ্রাহক, আমরা দেখতে পাচ্ছি এ বিষয়ে আপনি ইতিমধ্যেই আমাদের জানিয়েছেন এবং আমাদের টিম আপনার ইস্যুটি নিয়ে কাজ করছেন। কনফিউশন এড়াতে ও দ্রুত সাপোর্ট নিশ্চিত করার জন্য অনুগ্রহপূর্বক যেকোন একটি সাপোর্ট চ্যানেলে কানেক্টেড থাকুন। যেহেতু আমরা সকল মেসেজকে একইসাথে গুরুত্ব দিয়ে থাকি তাই একই বিষয়ে একের অধিক চ্যানেলে ডুপ্লিকেট মেসেজ বা টিকিট করার প্রয়োজন হয় না। বুঝতে পারার জন্য আন্তরিকভাবে ধন্যবাদ।",
    "addon": "To add an addon domain, go to the Domain option from the control panel.\r\nAnd watch this video.\r\nhttps://youtu.be/FhFF3-ISZpk\r\n\r\nTo understand in details, you can also watch: \r\nhttps://www.youtube.com/watch?v=NjtirDtnhaM&t=3s",
    "ssl": "আপনার ওয়েবসাইটে SSL একটিভ করার জন্য ৩৬ সেকেন্ডের এই ভিটিওটি দেখে খুব সহজেই বুঝতে পারবেন।\r\n\r\nhttps://www.youtube.com/watch?v=3zF3V91tEDs\r\n\r\nএসএসএল একটিভ করার পর থেকে ওয়েবসাইটে আপডেট হতে ৩০ মিনিট পর্যন্ত সময় নিবে।",
    "bujte": "I apologies that I didn't understand the matter. Can you explain a little more?",
    "check": "Thanks for your patience. Please check now.",
    "trialbn": "আমাদের ৩০ দিনের প্রশ্ন ছাড়া গ্যারান্টেড রিফান্ড পলিসি থাকায় স্ক্রিনশট, ট্রায়াল বা কোন ডেমো দেওয়ার প্রয়োজন হয় না।\r\n\r\nহোষ্টিং ক্রয়ের দিন থেকে ৩০ দিন পর্যন্ত আপনি যদি মনে করেন যে এটি আপনার জন্য প্রযোজ্য নয় তবে কোন প্রশ্নের উত্তর দেওয়া ছাড়া পুরো টাকা রিফান্ড নিতে পারবেন।",
    "trialen": "We provide a 30-day no-questions-asked refund policy, eliminating the need for screenshots, trials, or demos.\r\n\r\nIf our hosting services don't meet your needs, you can request a full refund within 30 days of purchase—no questions asked.",
    "trial": "আমাদের ৩০ দিনের প্রশ্ন ছাড়া গ্যারান্টেড রিফান্ড পলিসি থাকায় স্ক্রিনশট, ট্রায়াল বা কোন ডেমো দেওয়ার প্রয়োজন হয় না।\r\n\r\nহোষ্টিং ক্রয়ের দিন থেকে ৩০ দিন পর্যন্ত আপনি যদি মনে করেন যে এটি আপনার জন্য প্রযোজ্য নয় তবে কোন প্রশ্নের উত্তর দেওয়া ছাড়া পুরো টাকা রিফান্ড নিতে পারবেন।",
    "datacenter": "আমাদের বিভিন্ন ডাটাসেন্টারের সাথে পার্টনারশিপের মাধ্যমে সার্ভার রয়েছে। তন্মোধ্যে উল্লেখযোগ্য হলো:\r\n\r\n-OVHCloud\r\n-PhoneixNap\r\n-AWS\r\n-Hivelocity\r\n-Google Cloud\r\n-Hetzner GMBH\r\n-Contabo\r\n-Wolast Technologies",
    "hoodie": "আপনি যদি বেসিক ব্যতিত আমাদের যেকোন হোষ্টিং প্ল্যান একসাথে ৩ বছরের জন্য বুক করে থাকেন তবে ফ্রি হুডি ক্লেইম করতে পারবেন।",
    "amra": "আমরা ডোমেইন হোস্টিং ইন্ডাস্ট্রিতে ৫ বছরের বেশি সময় ধরে বিশ্বস্ততার সাথে সার্ভিস দিয়ে আসছি। গুগলে আমাদের নাম লিখে সার্চ করলে অসংখ্য পজিটিভ রিভিউ পেয়ে যাবেন, যা প্রমাণ করে আমাদের সেবা কতটা জনপ্রিয়।",
    "ipunblock": "আমি দেখতে পাচ্ছি আপনার ওয়েবসাইট কোন সমস্যা ছাড়া লোড হচ্ছে, এক্ষেত্রে আপনার আইপি ব্লক হতে পারে। অনুগ্রহপুর্বক নীচের লিংকে গিয়ে \"Share with Hostnin Team\" বাটনে ক্লিক করে আমাদের লিংকটি দিন। \r\n\r\nhttps://hostnin.com/ip",
    "support": "আমাদেব় ২৪/৭ সার্ভিস সাপোর্ট সিস্টেম ব়য়েছে। যেকোনো সময় যেকোনো ইস্যুতে ইনস্ট্যান্ট সাপোর্ট নিতে পাব়বেন",
    "supportall": "যেকোন সমস্যা বা সহযোগিতায় আমাদের রয়েছে ইন্সট্যান্ট সাপোর্ট সিস্টেম। সরাসরি কল, চ্যাট ও টিকিট সাপোর্ট থাকছে দিনের ২৪ ঘন্টা, সপ্তাহে ৭ দিন। \r\n\r\nএছাড়া সর্বোচ্চ ১ ঘন্টার মধ্যে টিকিট ও মেইল সাপোর্ট নিশ্চিত করা হয়।",
    "time": "Thank you for your patience. Still investigating. Please give me an additional 5-10 minutes.",
    "ultimate": "আমাদের এই প্যাকেজটি মান্থলী ১৯৯৯ টাকা। তবে ইয়ার্লীতে পার্চেস করলে ৬৭% ডিস্কাউন্টে মাত্র ৭৯৯২ টাকা আসবে। এছাড়া ট্রিনিয়ালি অর্থ্যাৎ তিন বছরে সবচেয়ে বেশি ডিস্কাউন্ট পাচ্ছেন। যেখানে ট্রিনিয়ালি পার্চেস করলে ৭৯% ডিস্কাউন্টে মাত্র ১৪৯৭৬ টাকায় বুক করতে পারবেন।\r\n\r\nট্রিনিয়ালী বুক করতে সাথে পাবেন এই ফ্রি .COM ডোমেইন , একটি হুডি , ফ্রি মাইগ্রেশন, ২০+ এসইও এবং পারফর্মেন্স টুলসের প্রিমিয়াম এক্সেস যা আপনার ওয়েবসাইটের র্যাঙ্কিংয়ে সহযোগিতা করবে।",
    "somoy": "Thank you for your time and cooperation.",
    "cloud": "আমাদের ক্লাউড বেইজড হোষ্টিং প্যাকেজগুলো পাবেন এই লিংকে:\r\nhttps://hostnin.com/hosting/cloud-hosting",
    "api": "বর্তমানে আমাদেব় API ব়িলেটেড কিছু ইস্যুব় কাব়নে সব়াসব়ি পোর্টাল নেমসার্ভাব় আপডেট কব়া যাচ্ছেনা। বিষয়টিব় জন্য আমব়া আন্তব়িকভাবে দুঃখিত। আপনাব় নেমসার্ভাব়গুলো আমাকে দিন আমি আপডেট  কব়া দিচ্ছি",
    "cpanelemail": "This video helps you to create a business email account:\r\nhttps://t.ly/czmUq"
  }
}